Workbook

Sheet Read Me
A1: AU Small Finance Bank Ltd (NSE: AUBANK) - Educational Bank Valuation Model
A2: Independent Educational Equity Research. This is not an investment advice, not a recommendation, not a target price.
A4: Valuation Date: 29-May-2026 (NSE closing price)
A5: Information Cut-Off: 29-May-2026 (No document published after this date is used in the valuation model)
A6: Accounting Basis: STANDALONE (AU reports as a single bank; Fincare SFB was amalgamated w.e.f. 01-Apr-2024 by pooling of interests method).
A7: Units: INR crores unless stated; Per-share data in INR; Ratios as decimals formatted %. Fiscal Year ends 31 March (FY26 = 01-Apr-2025 to 31-Mar-2026).
A8: Forecast: FY27E-FY31E Explicit; FY32-FY41 Fade Stage; Continuing Value thereafter (3-Stage Residual Income).
A10: Colour / Format Convention
A11: Blue Font = Hard-Coded Input (reported data or analyst assumption; every one carries a source ID or a note).
A12: Black Font = Formula Green Font = Formula linking to another sheet Yellow Fill = Key Assumption / Scenario Lever
A13: Grey Fill "Active" Rows = Drivers actually used by the Model (chosen by the scenario selector on Inputs).
A15: Sheet Map
... A29: - FY25 is not comparable with earlier years (Fincare amalgamation); FY21 includes a one-off gain on sale of Aavas stake (per company presentation) and Covid provisioning.

Sheet Inputs
A1: Inputs, Scenario Selector and Driver Tables
A2: Blue = input; yellow = key lever; grey "Active" rows feed the Model. Units: decimals shown as %, INR crore unless stated.
A4: A. Dates, market data and cost of equity
A5: Valuation Date | C5: 46171 | I5: NSE close. Information Cut-Off = Same Date.
A6: Base Balance-Sheet Date (FY26 Year-End) | C6: 46112 | I6: Audited standalone balance sheet [S1]
A7: Days from FY-end to Valuation Date | C7: =C5-C6 -> 59 | I7: Used to roll value from 31-Mar-2026 to valuation date
A8: Closing Price, 29-May-2026 (INR) | C8: 984.7 | I8: [S15] NSE EQ series close. 52-wk range 682.15-1,079.55
A9: Equity Shares Outstanding, 31-Mar-2026 (crores) | C9: =Hist!H36/10 -> 74.82671 | I9: Paid-up capital / face value INR10 [S1]
A10: Dilution from ESOPs (basic EPS / diluted EPS - 1) | C10: =Hist!H72/Hist!H73-1 -> 0.011139674 | I10: FY26 basic 35.40 / diluted 35.01 [S1]; applied to period-end shares
A11: Diluted shares for valuation (crore) | C11: =C9*(1+C10) -> 75.660255 | I11: Calculated
A12: Risk-free rate (10-yr G-sec, INR) | C12: 0.072 | I12: [S18] Interpolated: 7-yr 7.07% (22-May) and 14-yr 7.34% (29-May) RBI auction cut-offs -> ~7.19%; rounded 7.20%
A13: Equity beta (2-yr weekly vs NIFTY 50) | C13: =Beta!F4 -> 1.0232624 | I13: [S15][S16] Regression beta, see Beta sheet
A14: Equity risk premium (India, INR) | C14: 0.06 | I14: Analyst assumption (judgement; common practitioner range 5-7%). Sensitised in Valuation tables.
A15: Cost of equity (CAPM) | C15: =C12+C13*C14 -> 0.13339575 | I15: Rf + beta x ERP
A17: B. Scenario selector
A18: Scenario selector (1 = Base, 2 = Upside, 3 = Downside) | C18: 1 | I18: Drives every "Active" row below
A20: C. Terminal / valuation assumptions (by scenario)
A21: Item | C21: Base | D21: Upside | E21: Downside | F21: Active
A22: Terminal (steady-state) ROE | C22: 0.15 | D22: 0.165 | E22: 0.13 | F22: =CHOOSE($C$18,C22,D22,E22) -> 0.15 | I22: Judgement: FY22-FY26 reported ROE 13-16% (S8 extract); peer private banks 11-13%; universal-bank transition adds competition. Terminal ROE applies after a 10-year linear fade.
A23: Terminal growth of book value / earnings | C23: 0.07 | D23: 0.075 | E23: 0.065 | F23: =CHOOSE($C$18,C23,D23,E23) -> 0.07 | I23: Below long-run nominal GDP; must be < CoE and consistent with ROE x retention (implied payout = 1 - g/ROE)
A24: Fade period (years, FY32-FY41) - structural | C24: =COUNT(Valuation!H16:Q16) -> 10 | I24: Number of fade columns on Valuation sheet.
A26: D. Regulatory and structural inputs
A27: Assumed universal-bank transition: first fiscal year (e.g. 2028 = FY28) | C27: 2028 | I27: Assumption. In-principle approval 7-Aug-2025 [S14]; final application filed Mar-2026 [S1].
A28: Operational-risk capital proxy: % of avg gross income (BIA-style) | C28: 0.15 | I28: Assumption for illustration; RWA = 12.5 x alpha x 3-yr avg (NII + other income)
A29: SFB minimum CET1 | C29: 0.06 | I29: [S6]
A30: SFB minimum Tier 1 | C30: 0.075 | I30: [S6]
A31: SFB minimum CRAR | C31: 0.15 | I31: [S6]
A32: Universal bank minimum CET1 incl. CCB | C32: 0.08 | I32: [S19] 5.5% + 2.5% CCB
A33: Universal bank minimum Tier 1 incl. CCB | C33: 0.095 | I33: [S19] 7% + 2.5% CCB
A34: Universal bank minimum CRAR incl. CCB | C34: 0.115 | I34: [S19] 9% + 2.5% CCB
A35: Internal CET1 floor used in capital check | C35: 0.12 | I35: Analyst assumption (management buffer)
A36: Minimum cash & bank balances / deposits (CRR proxy) | C36: 0.03 | I36: Assumption approximating CRR
A37: Maximum net advances / deposits (funding check) | C37: 0.92 | I37: Analyst limit for the funding-supportability check
A39: E. Driver tables FY27E-FY31E (Base / Upside / Downside / Active)
A40: Driver | B40: Case | C40: FY27E | D40: FY28E | E40: FY29E | F40: FY30E | G40: FY31E | H40: FY26A | I40: Rationale / evidence
A41: Loan growth - Retail Secured (Wheels, MBL, Housing, Gold) | B41: Base | C41: 0.2 | D41: 0.18 | E41: 0.17 | F41: 0.16 | G41: 0.15 | I41: FY26 +21.0% [S8]. Base fades toward ~15%; growth rate = lower end of management "2-2.5x nominal GDP" [S10]
B42: Upside | C42: 0.24 | D42: 0.22 | E42: 0.21 | F42: 0.2 | G42: 0.18
B43: Downside | C43: 0.1 | D43: 0.12 | E43: 0.15 | F43: 0.15 | G43: 0.14
B44: Active | C44: =CHOOSE($C$18,C41,C42,C43) -> 0.2 | D44: =CHOOSE($C$18,D41,D42,D43) -> 0.18 | E44: =CHOOSE($C$18,E41,E42,E43) -> 0.17 | F44: =CHOOSE($C$18,F41,F42,F43) -> 0.16 | G44: =CHOOSE($C$18,G41,G42,G43) -> 0.15 | H44: =Model!E13/Model!D13-1 -> 0.21047823
A46: Loan growth - Commercial Banking | B46: Base | C46: 0.25 | D46: 0.21 | E46: 0.2 | F46: 0.18 | G46: 0.16 | I46: FY26 +29.3% [S8]; base fade towards 15-16%
B47: Upside | C47: 0.29 | D47: 0.26 | E47: 0.24 | F47: 0.22 | G47: 0.21
B48: Downside | C48: 0.14 | D48: 0.15 | E48: 0.17 | F48: 0.17 | G48: 0.16
B49: Active | C49: =CHOOSE($C$18,C46,C47,C48) -> 0.25 | D49: =CHOOSE($C$18,D46,D47,D48) -> 0.21 | E49: =CHOOSE($C$18,E46,E47,E48) -> 0.2 | F49: =CHOOSE($C$18,F46,F47,F48) -> 0.18 | G49: =CHOOSE($C$18,G46,G47,G48) -> 0.16 | H49: =Model!E14/Model!D14-1 -> 0.29291917
A51: Loan growth - Inclusive Banking (MFI) | B51: Base | C51: 0.05 | D51: 0.08 | E51: 0.12 | F51: 0.12 | G51: 0.12 | I51: FY26 +3.1%; growth build-up after continued stress [S10]
B52: Upside | C52: 0.12 | D52: 0.16 | E52: 0.16 | F52: 0.16 | G52: 0.16
B53: Downside | C53: -0.1 | D53: 0 | E53: 0.08 | F53: 0.1 | G53: 0.1
B54: Active | C54: =CHOOSE($C$18,C51,C52,C53) -> 0.05 | D54: =CHOOSE($C$18,D51,D52,D53) -> 0.08 | E54: =CHOOSE($C$18,E51,E52,E53) -> 0.12 | F54: =CHOOSE($C$18,F51,F52,F53) -> 0.12 | G54: =CHOOSE($C$18,G51,G52,G53) -> 0.12 | H54: =Model!E15/Model!D15-1 -> 0.030704916
A56: Loan growth - Digital Unsecured (cards, PL) | B56: Base | C56: 0 | D56: 0.1 | E56: 0.15 | F56: 0.15 | G56: 0.15 | I56: FY26 -10.4% (run-down/tightening) [S8]
B57: Upside | C57: 0.05 | D57: 0.15 | E57: 0.2 | F57: 0.2 | G57: 0.2
B58: Downside | C58: -0.15 | D58: -0.05 | E58: 0.08 | F58: 0.1 | G58: 0.1
B59: Active | C59: =CHOOSE($C$18,C56,C57,C58) -> 0 | D59: =CHOOSE($C$18,D56,D57,D58) -> 0.1 | E59: =CHOOSE($C$18,E56,E57,E58) -> 0.15 | F59: =CHOOSE($C$18,F56,F57,F58) -> 0.15 | G59: =CHOOSE($C$18,G56,G57,G58) -> 0.15 | H59: =Model!E16/Model!D16-1 -> -0.10364742
A61: Loan growth - Others & SME | B61: Base | C61: 0.2 | D61: 0.18 | E61: 0.16 | F61: 0.15 | G61: 0.15 | I61: FY26 +32.8% from small base [S8]
B62: Upside | C62: 0.24 | D62: 0.22 | E62: 0.2 | F62: 0.19 | G62: 0.19
B63: Downside | C63: 0.1 | D63: 0.12 | E63: 0.14 | F63: 0.14 | G63: 0.14
B64: Active | C64: =CHOOSE($C$18,C61,C62,C63) -> 0.2 | D64: =CHOOSE($C$18,D61,D62,D63) -> 0.18 | E64: =CHOOSE($C$18,E61,E62,E63) -> 0.16 | F64: =CHOOSE($C$18,F61,F62,F63) -> 0.15 | G64: =CHOOSE($C$18,G61,G62,G63) -> 0.15 | H64: =Model!E17/Model!D17-1 -> 0.32776533
A66: Net advances (balance sheet) / gross loan portfolio | B66: Base | C66: 0.957 | D66: 0.957 | E66: 0.957 | F66: 0.957 | G66: 0.957 | I66: FY26 0.957 (134,276 / 140,327); FY25 0.926. GLP includes off-book/IBPC items and is gross of provisions. Held constant (judgement)
B67: Upside | C67: 0.957 | D67: 0.957 | E67: 0.957 | F67: 0.957 | G67: 0.957
B68: Downside | C68: 0.95 | D68: 0.95 | E68: 0.952 | F68: 0.955 | G68: 0.955
B69: Active | C69: =CHOOSE($C$18,C66,C67,C68) -> 0.957 | D69: =CHOOSE($C$18,D66,D67,D68) -> 0.957 | E69: =CHOOSE($C$18,E66,E67,E68) -> 0.957 | F69: =CHOOSE($C$18,F66,F67,F68) -> 0.957 | G69: =CHOOSE($C$18,G66,G67,G68) -> 0.957 | H69: =Model!E20 -> 0.95687666
A71: Net advances / deposits (CD ratio) | B71: Base | C71: 0.88 | D71: 0.88 | E71: 0.88 | F71: 0.88 | G71: 0.88 | I71: FY26 88.0% on balance-sheet basis (company CD ex-refinance 80%, incl. refinance 88% [S8]). Deposit growth therefore tracks loan growth
B72: Upside | C72: 0.89 | D72: 0.89 | E72: 0.89 | F72: 0.89 | G72: 0.89
B73: Downside | C73: 0.86 | D73: 0.86 | E73: 0.87 | F73: 0.87 | G73: 0.87
B74: Active | C74: =CHOOSE($C$18,C71,C72,C73) -> 0.88 | D74: =CHOOSE($C$18,D71,D72,D73) -> 0.88 | E74: =CHOOSE($C$18,E71,E72,E73) -> 0.88 | F74: =CHOOSE($C$18,F71,F72,F73) -> 0.88 | G74: =CHOOSE($C$18,G71,G72,G73) -> 0.88 | H74: =Model!E26 -> 0.87956641
A76: CASA ratio | B76: Base | C76: 0.285 | D76: 0.29 | E76: 0.295 | F76: 0.3 | G76: 0.305 | I76: Mar-26 28.4% (43,357 / 152,661) [S9]; Mar-24 33%, Mar-23 38% [S11]. Slow rebuild assumed
B77: Upside | C77: 0.29 | D77: 0.3 | E77: 0.31 | F77: 0.32 | G77: 0.33
B78: Downside | C78: 0.27 | D78: 0.27 | E78: 0.275 | F78: 0.28 | G78: 0.285
B79: Active | C79: =CHOOSE($C$18,C76,C77,C78) -> 0.285 | D79: =CHOOSE($C$18,D76,D77,D78) -> 0.29 | E79: =CHOOSE($C$18,E76,E77,E78) -> 0.295 | F79: =CHOOSE($C$18,F76,F77,F78) -> 0.3 | G79: =CHOOSE($C$18,G76,G77,G78) -> 0.305 | H79: =Model!E28 -> 0.28400805
A81: Investments / deposits | B81: Base | C81: 0.29 | D81: 0.29 | E81: 0.29 | F81: 0.29 | G81: 0.29 | I81: FY22-FY26 range 28.9-31.1% (SLR plus non-SLR liquidity; LCR 119% Q4FY26 [S9])
B82: Upside | C82: 0.29 | D82: 0.29 | E82: 0.29 | F82: 0.29 | G82: 0.29
B83: Downside | C83: 0.3 | D83: 0.3 | E83: 0.3 | F83: 0.29 | G83: 0.29
B84: Active | C84: =CHOOSE($C$18,C81,C82,C83) -> 0.29 | D84: =CHOOSE($C$18,D81,D82,D83) -> 0.29 | E84: =CHOOSE($C$18,E81,E82,E83) -> 0.29 | F84: =CHOOSE($C$18,F81,F82,F83) -> 0.29 | G84: =CHOOSE($C$18,G81,G82,G83) -> 0.29 | H84: =Model!E40/Model!E25 -> 0.29341877
A86: Borrowings / deposits | B86: Base | C86: 0.09 | D86: 0.09 | E86: 0.09 | F86: 0.09 | G86: 0.09 | I86: FY26 9.1%; includes refinance and Tier 2
B87: Upside | C87: 0.09 | D87: 0.09 | E87: 0.09 | F87: 0.09 | G87: 0.09
B88: Downside | C88: 0.1 | D88: 0.1 | E88: 0.1 | F88: 0.095 | G88: 0.09
B89: Active | C89: =CHOOSE($C$18,C86,C87,C88) -> 0.09 | D89: =CHOOSE($C$18,D86,D87,D88) -> 0.09 | E89: =CHOOSE($C$18,E86,E87,E88) -> 0.09 | F89: =CHOOSE($C$18,F86,F87,F88) -> 0.09 | G89: =CHOOSE($C$18,G86,G87,G88) -> 0.09 | H89: =Model!E31/Model!E25 -> 0.090864922
A91: Other liabilities & provisions / deposits | B91: Base | C91: 0.035 | D91: 0.035 | E91: 0.035 | F91: 0.035 | G91: 0.035 | I91: FY26 3.47%
B92: Upside | C92: 0.035 | D92: 0.035 | E92: 0.035 | F92: 0.035 | G92: 0.035
B93: Downside | C93: 0.035 | D93: 0.035 | E93: 0.035 | F93: 0.035 | G93: 0.035
B94: Active | C94: =CHOOSE($C$18,C91,C92,C93) -> 0.035 | D94: =CHOOSE($C$18,D91,D92,D93) -> 0.035 | E94: =CHOOSE($C$18,E91,E92,E93) -> 0.035 | F94: =CHOOSE($C$18,F91,F92,F93) -> 0.035 | G94: =CHOOSE($C$18,G91,G92,G93) -> 0.035 | H94: =Model!E32/Model!E25 -> 0.034660013
A96: Other assets / net advances | B96: Base | C96: 0.021 | D96: 0.021 | E96: 0.021 | F96: 0.021 | G96: 0.021 | I96: FY26 2.06%
B97: Upside | C97: 0.021 | D97: 0.021 | E97: 0.021 | F97: 0.021 | G97: 0.021
B98: Downside | C98: 0.022 | D98: 0.022 | E98: 0.022 | F98: 0.022 | G98: 0.022
B99: Active | C99: =CHOOSE($C$18,C96,C97,C98) -> 0.021 | D99: =CHOOSE($C$18,D96,D97,D98) -> 0.021 | E99: =CHOOSE($C$18,E96,E97,E98) -> 0.021 | F99: =CHOOSE($C$18,F96,F97,F98) -> 0.021 | G99: =CHOOSE($C$18,G96,G97,G98) -> 0.021 | H99: =Model!E42/Model!E21 -> 0.020617249
A101: Fixed assets growth | B101: Base | C101: 0.1 | D101: 0.1 | E101: 0.1 | F101: 0.1 | G101: 0.1 | I101: FY26 +57% (step-up); normalised assumption
B102: Upside | C102: 0.1 | D102: 0.1 | E102: 0.1 | F102: 0.1 | G102: 0.1
B103: Downside | C103: 0.08 | D103: 0.08 | E103: 0.08 | F103: 0.08 | G103: 0.08
B104: Active | C104: =CHOOSE($C$18,C101,C102,C103) -> 0.1 | D104: =CHOOSE($C$18,D101,D102,D103) -> 0.1 | E104: =CHOOSE($C$18,E101,E102,E103) -> 0.1 | F104: =CHOOSE($C$18,F101,F102,F103) -> 0.1 | G104: =CHOOSE($C$18,G101,G102,G103) -> 0.1 | H104: =Model!E41/Model!D41-1 -> 0.57417729
A106: Yield on average net advances | B106: Base | C106: 0.1285 | D106: 0.128 | E106: 0.1275 | F106: 0.1275 | G106: 0.1275 | I106: FY26 13.02% (model def.; co. 13.1% [S8]). Q4FY26 GLP yield 13.8% but mix shifting to Commercial Banking (10.4%)
B107: Upside | C107: 0.129 | D107: 0.1288 | E107: 0.1285 | F107: 0.1285 | G107: 0.1285
B108: Downside | C108: 0.127 | D108: 0.126 | E108: 0.1255 | F108: 0.1255 | G108: 0.1255
B109: Active | C109: =CHOOSE($C$18,C106,C107,C108) -> 0.1285 | D109: =CHOOSE($C$18,D106,D107,D108) -> 0.128 | E109: =CHOOSE($C$18,E106,E107,E108) -> 0.1275 | F109: =CHOOSE($C$18,F106,F107,F108) -> 0.1275 | G109: =CHOOSE($C$18,G106,G107,G108) -> 0.1275 | H109: =Model!E54 -> 0.1301838
A111: Yield on average investments | B111: Base | C111: 0.063 | D111: 0.063 | E111: 0.063 | F111: 0.063 | G111: 0.063 | I111: FY26 6.41%; FY22-FY26 5.98-6.92%
B112: Upside | C112: 0.063 | D112: 0.063 | E112: 0.063 | F112: 0.063 | G112: 0.063
B113: Downside | C113: 0.063 | D113: 0.063 | E113: 0.063 | F113: 0.063 | G113: 0.063
B114: Active | C114: =CHOOSE($C$18,C111,C112,C113) -> 0.063 | D114: =CHOOSE($C$18,D111,D112,D113) -> 0.063 | E114: =CHOOSE($C$18,E111,E112,E113) -> 0.063 | F114: =CHOOSE($C$18,F111,F112,F113) -> 0.063 | G114: =CHOOSE($C$18,G111,G112,G113) -> 0.063 | H114: =Model!E55 -> 0.064065096
A116: Yield on opening cash & bank balances (incl. other interest) | B116: Base | C116: 0.03 | D116: 0.03 | E116: 0.03 | F116: 0.03 | G116: 0.03 | I116: FY26 2.94% on opening balance. Opening balance used to avoid circularity
B117: Upside | C117: 0.03 | D117: 0.03 | E117: 0.03 | F117: 0.03 | G117: 0.03
B118: Downside | C118: 0.03 | D118: 0.03 | E118: 0.03 | F118: 0.03 | G118: 0.03
B119: Active | C119: =CHOOSE($C$18,C116,C117,C118) -> 0.03 | D119: =CHOOSE($C$18,D116,D117,D118) -> 0.03 | E119: =CHOOSE($C$18,E116,E117,E118) -> 0.03 | F119: =CHOOSE($C$18,F116,F117,F118) -> 0.03 | G119: =CHOOSE($C$18,G116,G117,G118) -> 0.03 | H119: =Model!E56 -> 0.029369499
A121: Cost of funds (interest expended / avg deposits + borrowings) | B121: Base | C121: 0.061 | D121: 0.0605 | E121: 0.0605 | F121: 0.0605 | G121: 0.0605 | I121: FY26 6.30% (model def.; co. 6.75%, Q4 exit 6.49% [S8]); repo 5.25% per call [S10]. Management: CoF "may have bottomed"
...

Sheet Model
A1: Integrated Forecast (INR crore unless stated) - Scenario Shown: | F1: =CHOOSE(Inputs!C18,"BASE","UPSIDE","DOWNSIDE") -> BASE
A2: Columns C-E = actuals linked to Hist; F-J = forecasts driven by Inputs "Active" rows. Cash & bank is the balancing item.
A4: Line item | B4: Unit | C4: FY24A | D4: FY25A | E4: FY26A | F4: FY27E | G4: FY28E | H4: FY29E | I4: FY30E | J4: FY31E | K4: Notes
A5: Fiscal year (numeric) | C5: 2024 | D5: 2025 | E5: 2026 | F5: 2027 | G5: 2028 | H5: 2029 | I5: 2030 | J5: 2031
A6: Loan book (gross loan portfolio by segment, reported for Mar-25 and Mar-26 [S8])
A7: Segment growth drivers are on Inputs; segment yields (Mar-26): RSA 14.2%, CB 10.4%, IB 25.2%, DU 14.2%, O&SME 8.0% [S8]
A13: GLP - Retail Secured Assets | B13: Rs cr | D13: 76616 | E13: 92742 | F13: =E13*(1+Inputs!C44) -> 111290.4 | G13: =F13*(1+Inputs!D44) -> 131322.67 | H13: =G13*(1+Inputs!E44) -> 153647.53 | I13: =H13*(1+Inputs!F44) -> 178231.13 | J13: =I13*(1+Inputs!G44) -> 204965.8 | K13: [S8] loan-mix slide
A14: GLP - Commercial Banking | B14: Rs cr | D14: 23952 | E14: 30968 | F14: =E14*(1+Inputs!C49) -> 38710 | G14: =F14*(1+Inputs!D49) -> 46839.1 | H14: =G14*(1+Inputs!E49) -> 56206.92 | I14: =H14*(1+Inputs!F49) -> 66324.166 | J14: =I14*(1+Inputs!G49) -> 76936.032 | K14: [S8] loan-mix slide
A15: GLP - Inclusive Banking (MFI) | B15: Rs cr | D15: 6937 | E15: 7150 | F15: =E15*(1+Inputs!C54) -> 7507.5 | G15: =F15*(1+Inputs!D54) -> 8108.1 | H15: =G15*(1+Inputs!E54) -> 9081.072 | I15: =H15*(1+Inputs!F54) -> 10170.801 | J15: =I15*(1+Inputs!G54) -> 11391.297 | K15: [S8] loan-mix slide
A16: GLP - Digital Unsecured | B16: Rs cr | D16: 3290 | E16: 2949 | F16: =E16*(1+Inputs!C59) -> 2949 | G16: =F16*(1+Inputs!D59) -> 3243.9 | H16: =G16*(1+Inputs!E59) -> 3730.485 | I16: =H16*(1+Inputs!F59) -> 4290.0577 | J16: =I16*(1+Inputs!G59) -> 4933.5664 | K16: [S8] loan-mix slide
A17: GLP - Others & SME | B17: Rs cr | D17: 4909 | E17: 6518 | F17: =E17*(1+Inputs!C64) -> 7821.6 | G17: =F17*(1+Inputs!D64) -> 9229.488 | H17: =G17*(1+Inputs!E64) -> 10706.206 | I17: =H17*(1+Inputs!F64) -> 12312.137 | J17: =I17*(1+Inputs!G64) -> 14158.958 | K17: [S8] loan-mix slide
A18: Gross loan portfolio (GLP) | B18: Rs cr | C18: =Hist!F47 -> 73999 | D18: =SUM(D13:D17) -> 115704 | E18: =SUM(E13:E17) -> 140327 | F18: =SUM(F13:F17) -> 168278.5 | G18: =SUM(G13:G17) -> 198743.26 | H18: =SUM(H13:H17) -> 233372.21 | I18: =SUM(I13:I17) -> 271328.29 | J18: =SUM(J13:J17) -> 312385.65 | K18: Mar-24 per [S11]; ties to reported 140,327 / 115,704
A19: GLP growth | B19: % | D19: =D18/C18-1 -> 0.5635887 | E19: =E18/D18-1 -> 0.21281027 | F19: =F18/E18-1 -> 0.19918832 | G19: =G18/F18-1 -> 0.18103774 | H19: =H18/G18-1 -> 0.17423962 | I19: =I18/H18-1 -> 0.16264183 | J19: =J18/I18-1 -> 0.15131987 | K19: FY25 includes Fincare book
A20: Net advances / GLP | B20: x | C20: =C21/C18 -> 0.98869788 | D20: =D21/D18 -> 0.92557288 | E20: =E21/E18 -> 0.95687666 | F20: =Inputs!C69 -> 0.957 | G20: =Inputs!D69 -> 0.957 | H20: =Inputs!E69 -> 0.957 | I20: =Inputs!F69 -> 0.957 | J20: =Inputs!G69 -> 0.957
A21: Net advances (balance sheet) | B21: Rs cr | C21: =Hist!F32 -> 73162.655 | D21: =Hist!G32 -> 107092.48 | E21: =Hist!H32 -> 134275.63 | F21: =F18*F20 -> 161042.52 | G21: =G18*G20 -> 190197.3 | H21: =H18*H20 -> 223337.2 | I21: =I18*I20 -> 259661.17 | J21: =J18*J20 -> 298953.07
A22: Net advances growth | B22: % | D22: =D21/C21-1 -> 0.46375887 | E22: =E21/D21-1 -> 0.2538287 | F22: =F21/E21-1 -> 0.1993429 | G22: =G21/F21-1 -> 0.18103774 | H22: =H21/G21-1 -> 0.17423962 | I22: =I21/H21-1 -> 0.16264183 | J22: =J21/I21-1 -> 0.15131987
A24: Funding
A25: Deposits | B25: Rs cr | C25: =Hist!F40 -> 87182.116 | D25: =Hist!G40 -> 124268.54 | E25: =Hist!H40 -> 152661.16 | F25: =F21/F26 -> 183002.87 | G25: =G21/G26 -> 216133.3 | H25: =H21/H26 -> 253792.28 | I25: =I21/I26 -> 295069.52 | J25: =J21/J26 -> 339719.4 | K25: Deposits = net advances / CD ratio
A26: Net advances / deposits | B26: % | C26: =C21/C25 -> 0.83919338 | D26: =D21/D25 -> 0.86178273 | E26: =E21/E25 -> 0.87956641 | F26: =Inputs!C74 -> 0.88 | G26: =Inputs!D74 -> 0.88 | H26: =Inputs!E74 -> 0.88 | I26: =Inputs!F74 -> 0.88 | J26: =Inputs!G74 -> 0.88
A27: CASA deposits | B27: Rs cr | C27: =Hist!F48 -> 29126 | E27: =Hist!H48 -> 43357 | F27: =F25*F28 -> 52155.818 | G27: =G25*G28 -> 62678.656 | H27: =H25*H28 -> 74868.722 | I27: =I25*I28 -> 88520.855 | J27: =J25*J28 -> 103614.42
A28: CASA ratio | B28: % | C28: =C27/C25 -> 0.33408228 | E28: =E27/E25 -> 0.28400805 | F28: =Inputs!C79 -> 0.285 | G28: =Inputs!D79 -> 0.29 | H28: =Inputs!E79 -> 0.295 | I28: =Inputs!F79 -> 0.3 | J28: =Inputs!G79 -> 0.305
A29: Term deposits (incl. CDs) | B29: Rs cr | C29: =C25-C27 -> 58056.116 | E29: =E25-E27 -> 109304.16 | F29: =F25-F27 -> 130847.05 | G29: =G25-G27 -> 153454.64 | H29: =H25-H27 -> 178923.56 | I29: =I25-I27 -> 206548.66 | J29: =J25-J27 -> 236104.98
A30: Deposit growth | B30: % | D30: =D25/C25-1 -> 0.42539031 | E30: =E25/D25-1 -> 0.22847793 | F30: =F25/E25-1 -> 0.19875196 | G30: =G25/F25-1 -> 0.18103774 | H30: =H25/G25-1 -> 0.17423962 | I30: =I25/H25-1 -> 0.16264183 | J30: =J25/I25-1 -> 0.15131987
A31: Borrowings | B31: Rs cr | C31: =Hist!F41 -> 5479.3721 | D31: =Hist!G41 -> 11659.902 | E31: =Hist!H41 -> 13871.545 | F31: =F25*Inputs!C89 -> 16470.258 | G31: =G25*Inputs!D89 -> 19451.997 | H31: =H25*Inputs!E89 -> 22841.305 | I31: =I25*Inputs!F89 -> 26556.257 | J31: =J25*Inputs!G89 -> 30574.746 | K31: Ratio to deposits (Inputs)
A32: Other liabilities & provisions | B32: Rs cr | C32: =Hist!F42 -> 4204.6499 | D32: =Hist!G42 -> 4750.9383 | E32: =Hist!H42 -> 5291.2379 | F32: =F25*Inputs!C94 -> 6405.1004 | G32: =G25*Inputs!D94 -> 7564.6653 | H32: =H25*Inputs!E94 -> 8882.7297 | I32: =I25*Inputs!F94 -> 10327.433 | J32: =J25*Inputs!G94 -> 11890.179
A33: Shareholders' funds (from equity roll-forward) | B33: Rs cr | C33: =Hist!F39 -> 12559.532 | D33: =Hist!G39 -> 17166.282 | E33: =Hist!H39 -> 19973.522 | F33: =F80 -> 23622.054 | G33: =G80 -> 28130.061 | H33: =H80 -> 33552.506 | I33: =I80 -> 40011.329 | J33: =J80 -> 47661.969
A34: Total liabilities & equity | B34: Rs cr | C34: =C25+C31+C32+C33 -> 109425.67 | D34: =D25+D31+D32+D33 -> 157845.67 | E34: =E25+E31+E32+E33 -> 191797.47 | F34: =F25+F31+F32+F33 -> 229500.28 | G34: =G25+G31+G32+G33 -> 271280.02 | H34: =H25+H31+H32+H33 -> 319068.82 | I34: =I25+I31+I32+I33 -> 371964.54 | J34: =J25+J31+J32+J33 -> 429846.29
A36: Assets
A37: Cash & balances with RBI | B37: Rs cr | C37: =Hist!F29 -> 4638.0094 | D37: =Hist!G29 -> 8604.6221 | E37: =Hist!H29 -> 6973.2602 | K37: Actuals only; forecast shown combined in row 39
A38: Balances with banks & money at call | B38: Rs cr | C38: =Hist!F30 -> 1738.3249 | D38: =Hist!G30 -> 861.7397 | E38: =Hist!H30 -> 1550.1495
A39: Cash & bank balances (BALANCING ITEM) | B39: Rs cr | C39: =C37+C38 -> 6376.3343 | D39: =D37+D38 -> 9466.3618 | E39: =E37+E38 -> 8523.4097 | F39: =F34-F21-F40-F41-F42 -> 10425.012 | G39: =G34-G21-G40-G41-G42 -> 12671.897 | H39: =H34-H21-H40-H41-H42 -> 15529.947 | I39: =I34-I21-I40-I41-I42 -> 19177.31 | J39: =J34-J21-J40-J41-J42 -> 23783.274 | K39: Plug = total L&E - other assets; tested against minimum liquidity
A40: Investments | B40: Rs cr | C40: =Hist!F31 -> 27133.365 | D40: =Hist!G31 -> 37847.524 | E40: =Hist!H31 -> 44793.651 | F40: =F25*Inputs!C84 -> 53070.832 | G40: =G25*Inputs!D84 -> 62678.656 | H40: =H25*Inputs!E84 -> 73599.761 | I40: =I25*Inputs!F84 -> 85570.16 | J40: =J25*Inputs!G84 -> 98518.625
A41: Fixed assets | B41: Rs cr | C41: =Hist!F33 -> 851.5924 | D41: =Hist!G33 -> 912.4652 | E41: =Hist!H33 -> 1436.382 | F41: =E41*(1+Inputs!C104) -> 1580.0202 | G41: =F41*(1+Inputs!D104) -> 1738.0222 | H41: =G41*(1+Inputs!E104) -> 1911.8244 | I41: =H41*(1+Inputs!F104) -> 2103.0069 | J41: =I41*(1+Inputs!G104) -> 2313.3076
A42: Other assets | B42: Rs cr | C42: =Hist!F34 -> 1901.7232 | D42: =Hist!G34 -> 2526.8312 | E42: =Hist!H34 -> 2768.3941 | F42: =F21*Inputs!C99 -> 3381.893 | G42: =G21*Inputs!D99 -> 3994.1433 | H42: =H21*Inputs!E99 -> 4690.0813 | I42: =I21*Inputs!F99 -> 5452.8847 | J42: =J21*Inputs!G99 -> 6278.0145
A43: Total assets | B43: Rs cr | C43: =C21+C39+C40+C41+C42 -> 109425.67 | D43: =D21+D39+D40+D41+D42 -> 157845.67 | E43: =E21+E39+E40+E41+E42 -> 191797.47 | F43: =F21+F39+F40+F41+F42 -> 229500.28 | G43: =G21+G39+G40+G41+G42 -> 271280.02 | H43: =H21+H39+H40+H41+H42 -> 319068.82 | I43: =I21+I39+I40+I41+I42 -> 371964.54 | J43: =J21+J39+J40+J41+J42 -> 429846.29
A44: Balance check: assets - (liabilities + equity) | B44: Rs cr | C44: =ROUND(C43-C34,2) -> 0 | D44: =ROUND(D43-D34,2) -> 0 | E44: =ROUND(E43-E34,2) -> 0 | F44: =ROUND(F43-F34,2) -> 0 | G44: =ROUND(G43-G34,2) -> 0 | H44: =ROUND(H43-H34,2) -> 0 | I44: =ROUND(I43-I34,2) -> 0 | J44: =ROUND(J43-J34,2) -> 0 | K44: Must be 0
A45: Non-cash assets (adv + inv + fixed + other) | B45: Rs cr | C45: =C21+C40+C41+C42 -> 103049.34 | D45: =D21+D40+D41+D42 -> 148379.3 | E45: =E21+E40+E41+E42 -> 183274.06 | F45: =F21+F40+F41+F42 -> 219075.27 | G45: =G21+G40+G41+G42 -> 258608.12 | H45: =H21+H40+H41+H42 -> 303538.87 | I45: =I21+I40+I41+I42 -> 352787.23 | J45: =J21+J40+J41+J42 -> 406063.02 | K45: Driver base for other income and opex (avoids circularity)
A46: Interest-earning assets (adv + inv + cash & bank) | B46: Rs cr | C46: =C21+C39+C40 -> 106672.35 | D46: =D21+D39+D40 -> 154406.37 | E46: =E21+E39+E40 -> 187592.69 | F46: =F21+F39+F40 -> 224538.37 | G46: =G21+G39+G40 -> 265547.85 | H46: =H21+H39+H40 -> 312466.91 | I46: =I21+I39+I40 -> 364408.64 | J46: =J21+J39+J40 -> 421254.97
A47: Cash & bank / deposits (vs minimum on Inputs) | B47: % | C47: =C39/C25 -> 0.073138099 | D47: =D39/D25 -> 0.076176653 | E47: =E39/E25 -> 0.055832207 | F47: =F39/F25 -> 0.056966386 | G47: =G39/G25 -> 0.058630008 | H47: =H39/H25 -> 0.061191568 | I47: =I39/I25 -> 0.064992514 | J47: =J39/J25 -> 0.070008584
A49: Income statement
A50: Interest on advances | B50: Rs cr | C50: =Hist!F6 -> 8442.1476 | D50: =Hist!G6 -> 13368.347 | E50: =Hist!H6 -> 15711.109 | F50: =F54*(F21+E21)/2 -> 18974.191 | G50: =G54*(G21+F21)/2 -> 22479.349 | H50: =H54*(H21+G21)/2 -> 26362.825 | I50: =I54*(I21+H21)/2 -> 30791.147 | J50: =J54*(J21+I21)/2 -> 35611.658
A51: Income on investments | B51: Rs cr | C51: =Hist!F7 -> 1632.3875 | D51: =Hist!G7 -> 2238.176 | E51: =Hist!H7 -> 2647.2074 | F51: =F55*(F40+E40)/2 -> 3082.7312 | G51: =G55*(G40+F40)/2 -> 3646.1089 | H51: =H55*(H40+G40)/2 -> 4292.7701 | I51: =I55*(I40+H40)/2 -> 5013.8525 | J51: =J55*(J40+I40)/2 -> 5798.7967
A52: Interest on RBI/bank balances & other interest | B52: Rs cr | C52: =Hist!F8+Hist!F9 -> 480.178 | D52: =Hist!G8+Hist!G9 -> 457.2078 | E52: =Hist!H8+Hist!H9 -> 278.0223 | F52: =F56*E39 -> 255.70229 | G52: =G56*F39 -> 312.75036 | H52: =H56*G39 -> 380.1569 | I52: =I56*H39 -> 465.89842 | J52: =J56*I39 -> 575.31929 | K52: On opening balance
A53: Interest earned | B53: Rs cr | C53: =SUM(C50:C52) -> 10554.713 | D53: =SUM(D50:D52) -> 16063.731 | E53: =SUM(E50:E52) -> 18636.339 | F53: =SUM(F50:F52) -> 22312.625 | G53: =SUM(G50:G52) -> 26438.208 | H53: =SUM(H50:H52) -> 31035.752 | I53: =SUM(I50:I52) -> 36270.898 | J53: =SUM(J50:J52) -> 41985.774
A54: Yield on avg net advances | B54: % | D54: =D50/((D21+C21)/2) -> 0.14832695 | E54: =E50/((E21+D21)/2) -> 0.1301838 | F54: =Inputs!C109 -> 0.1285 | G54: =Inputs!D109 -> 0.128 | H54: =Inputs!E109 -> 0.1275 | I54: =Inputs!F109 -> 0.1275 | J54: =Inputs!G109 -> 0.1275
A55: Yield on avg investments | B55: % | D55: =D51/((D40+C40)/2) -> 0.068887208 | E55: =E51/((E40+D40)/2) -> 0.064065096 | F55: =Inputs!C114 -> 0.063 | G55: =Inputs!D114 -> 0.063 | H55: =Inputs!E114 -> 0.063 | I55: =Inputs!F114 -> 0.063 | J55: =Inputs!G114 -> 0.063
A56: Yield on opening cash & bank | B56: % | D56: =D52/C39 -> 0.071703863 | E56: =E52/D39 -> 0.029369499 | F56: =Inputs!C119 -> 0.03 | G56: =Inputs!D119 -> 0.03 | H56: =Inputs!E119 -> 0.03 | I56: =Inputs!F119 -> 0.03 | J56: =Inputs!G119 -> 0.03
A57: Interest expended | B57: Rs cr | C57: =Hist!F11 -> 5397.6293 | D57: =Hist!G11 -> 8052.1494 | E57: =Hist!H11 -> 9523.6562 | F57: =F58*(F25+F31+E25+E31)/2 -> 11163.178 | G57: =G58*(G25+G31+F25+F31)/2 -> 13160.517 | H57: =H58*(H25+H31+G25+G31)/2 -> 15494.621 | I57: =I58*(I25+I31+H25+H31)/2 -> 18097.346 | J57: =J58*(J25+J31+I25+I31)/2 -> 20930.577
A58: Cost of funds (avg deposits + borrowings) | B58: % | D58: =D57/((D25+D31+C25+C31)/2) -> 0.070450603 | E58: =E57/((E25+E31+D25+D31)/2) -> 0.062974409 | F58: =Inputs!C124 -> 0.061 | G58: =Inputs!D124 -> 0.0605 | H58: =Inputs!E124 -> 0.0605 | I58: =Inputs!F124 -> 0.0605 | J58: =Inputs!G124 -> 0.0605
A59: Net interest income | B59: Rs cr | C59: =C53-C57 -> 5157.0838 | D59: =D53-D57 -> 8011.5815 | E59: =E53-E57 -> 9112.6828 | F59: =F53-F57 -> 11149.447 | G59: =G53-G57 -> 13277.691 | H59: =H53-H57 -> 15541.131 | I59: =I53-I57 -> 18173.552 | J59: =J53-J57 -> 21055.197
A60: Other income / avg non-cash assets | B60: % | D60: =D62/((D45+C45)/2) -> 0.020095651 | E60: =E62/((E45+D45)/2) -> 0.017958139 | F60: =Inputs!C129 -> 0.018 | G60: =Inputs!D129 -> 0.018 | H60: =Inputs!E129 -> 0.018 | I60: =Inputs!F129 -> 0.018 | J60: =Inputs!G129 -> 0.018
A61: Opex / avg non-cash assets | B61: % | D61: =D64/((D45+C45)/2) -> 0.047386927 | E61: =E64/((E45+D45)/2) -> 0.042223974 | F61: =Inputs!C134 -> 0.0415 | G61: =Inputs!D134 -> 0.0405 | H61: =Inputs!E134 -> 0.0395 | I61: =Inputs!F134 -> 0.0388 | J61: =Inputs!G134 -> 0.0382
A62: Other income (fees, treasury, PSLC etc.) | B62: Rs cr | C62: =Hist!F13 -> 1745.8928 | D62: =Hist!G13 -> 2526.3111 | E62: =Hist!H13 -> 2977.9386 | F62: =F60*(F45+E45)/2 -> 3621.144 | G62: =G60*(G45+F45)/2 -> 4299.1505 | H62: =H60*(H45+G45)/2 -> 5059.3229 | I62: =I60*(I45+H45)/2 -> 5906.9349 | J62: =J60*(J45+I45)/2 -> 6829.6522
A63: Credit cost (provisions / avg GLP) | B63: % | D63: =D66/((D18+C18)/2) -> 0.01889926 | E63: =E66/((E18+D18)/2) -> 0.012613428 | F63: =Inputs!C139 -> 0.012 | G63: =Inputs!D139 -> 0.012 | H63: =Inputs!E139 -> 0.012 | I63: =Inputs!F139 -> 0.012 | J63: =Inputs!G139 -> 0.012 | K63: FY25 distorted (opening GLP pre-merger)
A64: Operating expenses | B64: Rs cr | C64: =Hist!F17 -> 4388.0022 | D64: =Hist!G17 -> 5957.2153 | E64: =Hist!H17 -> 7001.8615 | F64: =F61*(F45+E45)/2 -> 8348.7486 | G64: =G61*(G45+F45)/2 -> 9673.0887 | H64: =H61*(H45+G45)/2 -> 11102.403 | I64: =I61*(I45+H45)/2 -> 12732.726 | J64: =J61*(J45+I45)/2 -> 14494.04
A65: Pre-provision operating profit | B65: Rs cr | C65: =C59+C62-C64 -> 2514.9744 | D65: =D59+D62-D64 -> 4580.6773 | E65: =E59+E62-E64 -> 5088.7599 | F65: =F59+F62-F64 -> 6421.8424 | G65: =G59+G62-G64 -> 7903.7527 | H65: =H59+H62-H64 -> 9498.0505 | I65: =I59+I62-I64 -> 11347.761 | J65: =J59+J62-J64 -> 13390.809
A66: Provisions & contingencies | B66: Rs cr | C66: =Hist!F19 -> 438.7439 | D66: =Hist!G19 -> 1792.6232 | E66: =Hist!H19 -> 1614.7143 | F66: =F63*(F18+E18)/2 -> 1851.633 | G66: =G63*(G18+F18)/2 -> 2202.1306 | H66: =H63*(H18+G18)/2 -> 2592.6928 | I66: =I63*(I18+H18)/2 -> 3028.203 | J66: =J63*(J18+I18)/2 -> 3502.2837
A67: Effective tax rate | B67: % | C67: =C69/C68 -> 0.23242139 | D67: =D69/D68 -> 0.24466078 | E67: =E69/E68 -> 0.23971801 | F67: =Inputs!C144 -> 0.24 | G67: =Inputs!D144 -> 0.24 | H67: =Inputs!E144 -> 0.24 | I67: =Inputs!F144 -> 0.24 | J67: =Inputs!G144 -> 0.24
A68: Profit before tax (after exceptional items) | B68: Rs cr | C68: =C65-C66-Hist!F20 -> 1999.4291 | D68: =D65-D66-Hist!G20 -> 2788.0541 | E68: =E65-E66-Hist!H20 -> 3474.0456 | F68: =F65-F66 -> 4570.2094 | G68: =G65-G66 -> 5701.6221 | H68: =H65-H66 -> 6905.3577 | I68: =I65-I66 -> 8319.5577 | J68: =J65-J66 -> 9888.5255 | K68: FY24 exceptional Rs76.8 cr
A69: Tax | B69: Rs cr | C69: =Hist!F22 -> 464.7101 | D69: =Hist!G22 -> 682.1275 | E69: =Hist!H22 -> 832.7913 | F69: =F68*F67 -> 1096.8503 | G69: =G68*G67 -> 1368.3893 | H69: =H68*H67 -> 1657.2859 | I69: =I68*I67 -> 1996.6938 | J69: =J68*J67 -> 2373.2461
A70: Net profit (PAT) | B70: Rs cr | C70: =C68-C69 -> 1534.719 | D70: =D68-D69 -> 2105.9266 | E70: =E68-E69 -> 2641.2543 | F70: =F68-F69 -> 3473.3592 | G70: =G68-G69 -> 4333.2328 | H70: =H68-H69 -> 5248.0719 | I70: =I68-I69 -> 6322.8638 | J70: =J68-J69 -> 7515.2794
A71: PAT growth | B71: % | D71: =D70/C70-1 -> 0.37219035 | E71: =E70/D70-1 -> 0.25420055 | F71: =F70/E70-1 -> 0.31504156 | G71: =G70/F70-1 -> 0.24756255 | H71: =H70/G70-1 -> 0.21112161 | I71: =I70/H70-1 -> 0.20479749 | J71: =J70/I70-1 -> 0.18858789
A73: Equity roll-forward and per-share data
A74: Opening shareholders funds | B74: Rs cr | F74: =E80 -> 19973.522 | G74: =F80 -> 23622.054 | H74: =G80 -> 28130.061 | I74: =H80 -> 33552.506 | J74: =I80 -> 40011.329
A75: Dividend per share declared for the year (INR) | B75: INR | C75: 1 | E75: 1 | F75: =Inputs!C149 -> 1 | G75: =Inputs!D149 -> 1 | H75: =Inputs!E149 -> 1.5 | I75: =Inputs!F149 -> 1.5 | J75: =Inputs!G149 -> 2 | K75: FY24, FY26 INR1 [S3][S1]; FY25 not captured
A76: Less: dividend paid in year (prior-year DPS x opening shares) | B76: Rs cr | F76: =IF(ISNUMBER(E75),E75,0)*E83 -> 74.82671 | G76: =IF(ISNUMBER(F75),F75,0)*F83 -> 75.22671 | H76: =IF(ISNUMBER(G75),G75,0)*G83 -> 75.62671 | I76: =IF(ISNUMBER(H75),H75,0)*H83 -> 114.04007 | J76: =IF(ISNUMBER(I75),I75,0)*I83 -> 114.64007
A77: Add: ESOP / other equity additions | B77: Rs cr | F77: =Inputs!C154 -> 250 | G77: =Inputs!D154 -> 250 | H77: =Inputs!E154 -> 250 | I77: =Inputs!F154 -> 250 | J77: =Inputs!G154 -> 250
A78: Add: new equity raised | B78: Rs cr | F78: =Inputs!C164 -> 0 | G78: =Inputs!D164 -> 0 | H78: =Inputs!E164 -> 0 | I78: =Inputs!F164 -> 0 | J78: =Inputs!G164 -> 0
A79: Add: PAT | B79: Rs cr | F79: =F70 -> 3473.3592 | G79: =G70 -> 4333.2328 | H79: =H70 -> 5248.0719 | I79: =I70 -> 6322.8638 | J79: =J70 -> 7515.2794
A80: Closing shareholders funds | B80: Rs cr | C80: =C33 -> 12559.532 | D80: =D33 -> 17166.282 | E80: =E33 -> 19973.522 | F80: =F74-F76+F77+F78+F79 -> 23622.054 | G80: =G74-G76+G77+G78+G79 -> 28130.061 | H80: =H74-H76+H77+H78+H79 -> 33552.506 | I80: =I74-I76+I77+I78+I79 -> 40011.329 | J80: =J74-J76+J77+J78+J79 -> 47661.969
A81: Share capital (shares x INR10) | B81: Rs cr | C81: =Hist!F36 -> 669.1625 | D81: =Hist!G36 -> 744.5305 | E81: =Hist!H36 -> 748.2671 | F81: =F83*10 -> 752.2671 | G81: =G83*10 -> 756.2671 | H81: =H83*10 -> 760.2671 | I81: =I83*10 -> 764.2671 | J81: =J83*10 -> 768.2671
A82: Reserves & surplus incl. ESOP o/s (roll-forward) | B82: Rs cr | C82: =Hist!F37+Hist!F38 -> 11890.369 | D82: =Hist!G37+Hist!G38 -> 16421.751 | E82: =Hist!H37+Hist!H38 -> 19225.255 | F82: =E82+F79-F76+F77+F78-(F81-E81) -> 22869.787 | G82: =F82+G79-G76+G77+G78-(G81-F81) -> 27373.793 | H82: =G82+H79-H76+H77+H78-(H81-G81) -> 32792.239 | I82: =H82+I79-I76+I77+I78-(I81-H81) -> 39247.062 | J82: =I82+J79-J76+J77+J78-(J81-I81) -> 46893.702 | K82: Opening + PAT - dividends + additions - face value of new shares
A83: Shares outstanding, period end (crore) | B83: cr | C83: =Hist!F36/10 -> 66.91625 | D83: =Hist!G36/10 -> 74.45305 | E83: =Hist!H36/10 -> 74.82671 | F83: =E83+Inputs!C159+IF(Inputs!C164>0,Inputs!C164/(Inputs!C169*E84),0) -> 75.22671 | G83: =F83+Inputs!D159+IF(Inputs!D164>0,Inputs!D164/(Inputs!D169*F84),0) -> 75.62671 | H83: =G83+Inputs!E159+IF(Inputs!E164>0,Inputs!E164/(Inputs!E169*G84),0) -> 76.02671 | I83: =H83+Inputs!F159+IF(Inputs!F164>0,Inputs!F164/(Inputs!F169*H84),0) -> 76.42671 | J83: =I83+Inputs!G159+IF(Inputs!G164>0,Inputs!G164/(Inputs!G169*I84),0) -> 76.82671
A84: Book value per share (INR) | B84: INR | C84: =C80/C83 -> 187.69031 | D84: =D80/D83 -> 230.56519 | E84: =E80/E83 -> 266.93038 | F84: =F80/F83 -> 314.01153 | G84: =G80/G83 -> 371.95933 | H84: =H80/H83 -> 441.32524 | I84: =I80/I83 -> 523.52547 | J84: =J80/J83 -> 620.38279
A85: EPS diluted (INR) | B85: INR | C85: =Hist!F73 -> 22.86 | D85: =Hist!G73 -> 28.24 | E85: =Hist!H73 -> 35.01 | F85: =F70/(((F83+E83)/2)*(1+Inputs!$C$10)) -> 45.784939 | G85: =G70/(((G83+F83)/2)*(1+Inputs!$C$10)) -> 56.816661 | H85: =H70/(((H83+G83)/2)*(1+Inputs!$C$10)) -> 68.44889 | I85: =I70/(((I83+H83)/2)*(1+Inputs!$C$10)) -> 82.034305 | J85: =J70/(((J83+I83)/2)*(1+Inputs!$C$10)) -> 96.995994 | K85: Avg shares x (1 + FY26 dilution)
A86: ROE (PAT / avg equity) | B86: % | D86: =D70/((D80+C80)/2) -> 0.14169009 | E86: =E70/((E80+D80)/2) -> 0.14223308 | F86: =F70/((F80+E80)/2) -> 0.15934457 | G86: =G70/((G80+F80)/2) -> 0.16746109 | H86: =H70/((H80+G80)/2) -> 0.17016386 | I86: =I70/((I80+H80)/2) -> 0.17190142 | J86: =J70/((J80+I80)/2) -> 0.17143827
A87: ROA (PAT / avg total assets) | B87: % | D87: =D70/((D43+C43)/2) -> 0.015758716 | E87: =E70/((E43+D43)/2) -> 0.015108286 | F87: =F70/((F43+E43)/2) -> 0.016488857 | G87: =G70/((G43+F43)/2) -> 0.017305924 | H87: =H70/((H43+G43)/2) -> 0.017779562 | I87: =I70/((I43+H43)/2) -> 0.018299736 | J87: =J70/((J43+I43)/2) -> 0.018745767
A88: Credit RWA / total assets | B88: % | C88: =Hist!F61 -> 0.58199169 | D88: =Hist!G61 -> 0.57063483 | E88: =Hist!H61 -> 0.60602458 | F88: =Inputs!C174 -> 0.61 | G88: =Inputs!D174 -> 0.61 | H88: =Inputs!E174 -> 0.61 | I88: =Inputs!F174 -> 0.61 | J88: =Inputs!G174 -> 0.61
A89: Risk-weighted assets and regulatory capital
A90: Credit RWA | B90: Rs cr | C90: =Hist!F57 -> 63684.831 | D90: =Hist!G57 -> 90072.234 | E90: =Hist!H57 -> 116233.98 | F90: =F43*F88 -> 139995.17 | G90: =G43*G88 -> 165480.81 | H90: =H43*H88 -> 194631.98 | I90: =I43*I88 -> 226898.37 | J90: =J43*J88 -> 262206.24
A91: Regulatory deductions / book equity | B91: % | C91: =(C80-C92)/C80 -> 0.046750255 | D91: =(D80-D92)/D80 -> 0.048176053 | E91: =(E80-E92)/E80 -> 0.019159966 | F91: =Inputs!C184 -> 0.02 | G91: =Inputs!D184 -> 0.02 | H91: =Inputs!E184 -> 0.02 | I91: =Inputs!F184 -> 0.02 | J91: =Inputs!G184 -> 0.02
A92: CET1 = Tier 1 capital | B92: Rs cr | C92: =Hist!F55 -> 11972.37 | D92: =Hist!G55 -> 16339.278 | E92: =Hist!H55 -> 19590.83 | F92: =F80*(1-F91) -> 23149.613 | G92: =G80*(1-G91) -> 27567.459 | H92: =H80*(1-H91) -> 32881.456 | I92: =I80*(1-I91) -> 39211.103 | J92: =J80*(1-J91) -> 46708.729
A93: Tier 2 capital | B93: Rs cr | C93: =Hist!F56 -> 800.8048 | D93: =Hist!G56 -> 1726.264 | E93: =Hist!H56 -> 2117.74 | F93: =F92*F94 -> 2500.1582 | G93: =G92*G94 -> 2977.2856 | H93: =H92*H94 -> 3551.1972 | I93: =I92*I94 -> 4234.7991 | J93: =J92*J94 -> 5044.5428
A94: Tier 2 / Tier 1 | B94: % | C94: =C93/C92 -> 0.066887741 | D94: =D93/D92 -> 0.10565118 | E94: =E93/E92 -> 0.10809853 | F94: =Inputs!C179 -> 0.108 | G94: =Inputs!D179 -> 0.108 | H94: =Inputs!E179 -> 0.108 | I94: =Inputs!F179 -> 0.108 | J94: =Inputs!G179 -> 0.108
A95: Gross income (NII + other income) | B95: Rs cr | C95: =C59+C62 -> 6902.9766 | D95: =D59+D62 -> 10537.893 | E95: =E59+E62 -> 12090.621 | F95: =F59+F62 -> 14770.591 | G95: =G59+G62 -> 17576.841 | H95: =H59+H62 -> 20600.454 | I95: =I59+I62 -> 24080.487 | J95: =J59+J62 -> 27884.849
A96: Universal bank flag (1 from transition year) | B96: flag | C96: 0 | D96: 0 | E96: 0 | F96: =IF(F5>=Inputs!$C$27,1,0) -> 0 | G96: =IF(G5>=Inputs!$C$27,1,0) -> 1 | H96: =IF(H5>=Inputs!$C$27,1,0) -> 1 | I96: =IF(I5>=Inputs!$C$27,1,0) -> 1 | J96: =IF(J5>=Inputs!$C$27,1,0) -> 1
A97: Operational-risk RWA (from transition) | B97: Rs cr | F97: =F96*12.5*Inputs!$C$28*AVERAGE(C95:E95) -> 0 | G97: =G96*12.5*Inputs!$C$28*AVERAGE(D95:F95) -> 23374.441 | H97: =H96*12.5*Inputs!$C$28*AVERAGE(E95:G95) -> 27773.784 | I97: =I96*12.5*Inputs!$C$28*AVERAGE(F95:H95) -> 33092.429 | J97: =J96*12.5*Inputs!$C$28*AVERAGE(G95:I95) -> 38911.114 | K97: 12.5 x alpha x avg gross income of prior 3 years (assumption)
A98: Total RWA | B98: Rs cr | C98: =C90 -> 63684.831 | D98: =D90 -> 90072.234 | E98: =E90 -> 116233.98 | F98: =F90+F97 -> 139995.17 | G98: =G90+G97 -> 188855.25 | H98: =H90+H97 -> 222405.76 | I98: =I90+I97 -> 259990.8 | J98: =J90+J97 -> 301117.35
A99: CET1 ratio (= Tier 1 ratio) | B99: % | C99: =C92/C98 -> 0.18799406 | D99: =D92/D98 -> 0.18140194 | E99: =E92/E98 -> 0.1685465 | F99: =F92/F98 -> 0.16536008 | G99: =G92/G98 -> 0.14597137 | H99: =H92/H98 -> 0.14784444 | I99: =I92/I98 -> 0.15081727 | J99: =J92/J98 -> 0.15511803
A100: CRAR | B100: % | C100: =(C92+C93)/C98 -> 0.20056856 | D100: =(D92+D93)/D98 -> 0.20056727 | E100: =(E92+E93)/E98 -> 0.18676612 | F100: =(F92+F93)/F98 -> 0.18321897 | G100: =(G92+G93)/G98 -> 0.16173628 | H100: =(H92+H93)/H98 -> 0.16381164 | I100: =(I92+I93)/I98 -> 0.16710554 | J100: =(J92+J93)/J98 -> 0.17187077
A101: Regulatory minimum CET1 | B101: % | C101: =Inputs!$C$29 -> 0.06 | D101: =Inputs!$C$29 -> 0.06 | E101: =Inputs!$C$29 -> 0.06 | F101: =IF(F96=1,Inputs!$C$32,Inputs!$C$29) -> 0.06 | G101: =IF(G96=1,Inputs!$C$32,Inputs!$C$29) -> 0.08 | H101: =IF(H96=1,Inputs!$C$32,Inputs!$C$29) -> 0.08 | I101: =IF(I96=1,Inputs!$C$32,Inputs!$C$29) -> 0.08 | J101: =IF(J96=1,Inputs!$C$32,Inputs!$C$29) -> 0.08
A102: Regulatory minimum Tier 1 | B102: % | C102: =Inputs!$C$30 -> 0.075 | D102: =Inputs!$C$30 -> 0.075 | E102: =Inputs!$C$30 -> 0.075 | F102: =IF(F96=1,Inputs!$C$33,Inputs!$C$30) -> 0.075 | G102: =IF(G96=1,Inputs!$C$33,Inputs!$C$30) -> 0.095 | H102: =IF(H96=1,Inputs!$C$33,Inputs!$C$30) -> 0.095 | I102: =IF(I96=1,Inputs!$C$33,Inputs!$C$30) -> 0.095 | J102: =IF(J96=1,Inputs!$C$33,Inputs!$C$30) -> 0.095
A103: Regulatory minimum CRAR | B103: % | C103: =Inputs!$C$31 -> 0.15 | D103: =Inputs!$C$31 -> 0.15 | E103: =Inputs!$C$31 -> 0.15 | F103: =IF(F96=1,Inputs!$C$34,Inputs!$C$31) -> 0.15 | G103: =IF(G96=1,Inputs!$C$34,Inputs!$C$31) -> 0.115 | H103: =IF(H96=1,Inputs!$C$34,Inputs!$C$31) -> 0.115 | I103: =IF(I96=1,Inputs!$C$34,Inputs!$C$31) -> 0.115 | J103: =IF(J96=1,Inputs!$C$34,Inputs!$C$31) -> 0.115
A104: CRAR headroom over minimum (pp) | B104: % | C104: =C100-C103 -> 0.050568562 | D104: =D100-D103 -> 0.050567268 | E104: =E100-E103 -> 0.036766125 | F104: =F100-F103 -> 0.033218973 | G104: =G100-G103 -> 0.046736275 | H104: =H100-H103 -> 0.04881164 | I104: =I100-I103 -> 0.052105539 | J104: =J100-J103 -> 0.056870774
A105: CET1 headroom over internal floor (pp) | B105: % | C105: =C99-Inputs!$C$35 -> 0.067994064 | D105: =D99-Inputs!$C$35 -> 0.06140194 | E105: =E99-Inputs!$C$35 -> 0.048546496 | F105: =F99-Inputs!$C$35 -> 0.045360084 | G105: =G99-Inputs!$C$35 -> 0.025971368 | H105: =H99-Inputs!$C$35 -> 0.027844441 | I105: =I99-Inputs!$C$35 -> 0.030817273 | J105: =J99-Inputs!$C$35 -> 0.035118027
A106: Capital surplus / (shortfall) vs binding requirement (Rs cr) | B106: Rs cr | C106: =MIN(C92+C93-C103*C98,C92-MAX(C102,Inputs!$C$35)*C98) -> 3220.4503 | D106: =MIN(D92+D93-D103*D98,D92-MAX(D102,Inputs!$C$35)*D98) -> 4554.7069 | E106: =MIN(E92+E93-E103*E98,E92-MAX(E102,Inputs!$C$35)*E98) -> 4273.473 | F106: =MIN(F92+F93-F103*F98,F92-MAX(F102,Inputs!$C$35)*F98) -> 4650.4958 | G106: =MIN(G92+G93-G103*G98,G92-MAX(G102,Inputs!$C$35)*G98) -> 4904.8292 | H106: =MIN(H92+H93-H103*H98,H92-MAX(H102,Inputs!$C$35)*H98) -> 6192.7641 | I106: =MIN(I92+I93-I103*I98,I92-MAX(I102,Inputs!$C$35)*I98) -> 8012.2074 | J106: =MIN(J92+J93-J103*J98,J92-MAX(J102,Inputs!$C$35)*J98) -> 10574.647 | K106: Min of total-capital and CET1/Tier-1 surplus; negative = equity must be raised
A107: Internal capital generation (retained PAT / opening equity) | B107: % | F107: =(F70-F76)/F74 -> 0.17015189 | G107: =(G70-G76)/G74 -> 0.18025554 | H107: =(H70-H76)/H74 -> 0.18387608 | I107: =(I70-I76)/I74 -> 0.18504799 | J107: =(J70-J76)/J74 -> 0.18496359
A108: RWA growth | B108: % | D108: =D98/C98-1 -> 0.41434362 | E108: =E98/D98-1 -> 0.29045294 | F108: =F98/E98-1 -> 0.20442552 | G108: =G98/F98-1 -> 0.3490126 | H108: =H98/G98-1 -> 0.17765199 | I108: =I98/H98-1 -> 0.16899307 | J108: =J98/I98-1 -> 0.15818466
A110: Asset quality (informational - does not drive P&L)
A111: Gross NPA | B111: Rs cr | C111: =Hist!F76 -> 1237.4004 | D111: =Hist!G76 -> 2477.0299 | E111: =Hist!H76 -> 2755.6406 | F111: =F18*Inputs!C189 -> 3365.57 | G111: =G18*Inputs!D189 -> 3974.8652 | H111: =H18*Inputs!E189 -> 4667.4442 | I111: =I18*Inputs!F189 -> 5426.5658 | J111: =J18*Inputs!G189 -> 6247.7131
...

Sheet Valuation
A1: Valuation - Residual Income (Primary) and Justified P/B-ROE (cross-check)
A2: =CONCATENATE("Scenario: ",Model!F1," | CoE ",TEXT(Inputs!C15,"0.00%")," | terminal ROE ",TEXT(Inputs!F22,"0.0%")," | terminal g ",TEXT(Inputs!F23,"0.0%")) -> Scenario: BASE | CoE 13.34% | terminal ROE 15.0% | terminal g 7.0%
A4: Key inputs
A5: Cost of equity | B5: =Inputs!C15 -> 0.13339575
A6: Terminal growth | B6: =Inputs!F23 -> 0.07
A7: Terminal ROE | B7: =Inputs!F22 -> 0.15
A8: Book value 31-Mar-2026 (Rs cr) | B8: =Model!E80 -> 19973.522
A9: Days 31-Mar-26 to valuation date | B9: =Inputs!C7 -> 59
A10: Diluted shares (cr) | B10: =Inputs!C11 -> 75.660255
A11: Share price (INR) | B11: =Inputs!C8 -> 984.7
A13: Stage 1 (explicit, Model) and Stage 2 (fade)
A14: Year | B14: FY26A | C14: FY27E | D14: FY28E | E14: FY29E | F14: FY30E | G14: FY31E | H14: FY32 | I14: FY33 | J14: FY34 | K14: FY35 | L14: FY36 | M14: FY37 | N14: FY38 | O14: FY39 | P14: FY40 | Q14: FY41
A15: Period index t (years from 31-Mar-2026) | C15: =B15+1 -> 1 | D15: =C15+1 -> 2 | E15: =D15+1 -> 3 | F15: =E15+1 -> 4 | G15: =F15+1 -> 5 | H15: =G15+1 -> 6 | I15: =H15+1 -> 7 | J15: =I15+1 -> 8 | ... Q15: =P15+1 -> 15
A16: Fade step i (0 in explicit stage) | C16: 0 | D16: 0 | E16: 0 | F16: 0 | G16: 0 | H16: =IF(H15>5,H15-5,0) -> 1 | I16: =IF(I15>5,I15-5,0) -> 2 | J16: =IF(J15>5,J15-5,0) -> 3 | K16: =IF(K15>5,K15-5,0) -> 4 | L16: =IF(L15>5,L15-5,0) -> 5 | M16: =IF(M15>5,M15-5,0) -> 6 | N16: =IF(N15>5,N15-5,0) -> 7 | O16: =IF(O15>5,O15-5,0) -> 8 | ... Q16: =IF(Q15>5,Q15-5,0) -> 10
A17: Opening book value | C17: =Model!F74 -> 19973.522 | D17: =Model!G74 -> 23622.054 | E17: =Model!H74 -> 28130.061 | F17: =Model!I74 -> 33552.506 | G17: =Model!J74 -> 40011.329 | H17: =G20 -> 47661.969 | I17: =H20 -> 56197.781 | J17: =I20 -> 65581.095 | K17: =J20 -> 75736.214 | L17: =K20 -> 86545.824 | M17: =L20 -> 97849.22 | N17: =M20 -> 109442.86 | O17: =N20 -> 121083.59 | ... Q17: =P20 -> 143375.42
A18: ROE on opening book value | C18: =C19/C17 -> 0.17389818 | D18: =D19/D17 -> 0.18344013 | E18: =E19/E17 -> 0.18656454 | F18: =F19/F17 -> 0.18844684 | G18: =G19/G17 -> 0.18782878 | H18: =$G$18+($B$7-$G$18)*H16/Inputs!$C$24 -> 0.18404591 | I18: =$G$18+($B$7-$G$18)*I16/Inputs!$C$24 -> 0.18026303 | J18: =$G$18+($B$7-$G$18)*J16/Inputs!$C$24 -> 0.17648015 | K18: =$G$18+($B$7-$G$18)*K16/Inputs!$C$24 -> 0.17269727 | L18: =$G$18+($B$7-$G$18)*L16/Inputs!$C$24 -> 0.16891439 | M18: =$G$18+($B$7-$G$18)*M16/Inputs!$C$24 -> 0.16513151 | N18: =$G$18+($B$7-$G$18)*N16/Inputs!$C$24 -> 0.16134864 | O18: =$G$18+($B$7-$G$18)*O16/Inputs!$C$24 -> 0.15756576 | ... Q18: =$G$18+($B$7-$G$18)*Q16/Inputs!$C$24 -> 0.15
A19: Net income | C19: =Model!F70 -> 3473.3592 | D19: =Model!G70 -> 4333.2328 | E19: =Model!H70 -> 5248.0719 | F19: =Model!I70 -> 6322.8638 | G19: =Model!J70 -> 7515.2794 | H19: =H18*H17 -> 8771.9902 | I19: =I18*I17 -> 10130.382 | J19: =J18*J17 -> 11573.761 | K19: =K18*K17 -> 13079.437 | L19: =L18*L17 -> 14618.835 | M19: =M18*M17 -> 16157.99 | N19: =N18*N17 -> 17658.456 | O19: =O18*O17 -> 19078.627 | ... Q19: =Q18*Q17 -> 21506.313
A20: Closing book value | B20: =Model!E80 -> 19973.522 | C20: =Model!F80 -> 23622.054 | D20: =Model!G80 -> 28130.061 | E20: =Model!H80 -> 33552.506 | F20: =Model!I80 -> 40011.329 | G20: =Model!J80 -> 47661.969 | H20: =H17*(1+H21) -> 56197.781 | I20: =I17*(1+I21) -> 65581.095 | J20: =J17*(1+J21) -> 75736.214 | K20: =K17*(1+K21) -> 86545.824 | L20: =L17*(1+L21) -> 97849.22 | M20: =M17*(1+M21) -> 109442.86 | N20: =N17*(1+N21) -> 121083.59 | O20: =O17*(1+O21) -> 132494.79 | ... Q20: =Q17*(1+Q21) -> 153411.7
A21: Book value growth | C21: =C20/C17-1 -> 0.18266846 | D21: =D20/D17-1 -> 0.19083887 | E21: =E20/E17-1 -> 0.19276337 | F21: =F20/F17-1 -> 0.192499 | G21: =G20/G17-1 -> 0.19121182 | H21: =$G$21+($B$6-$G$21)*H16/Inputs!$C$24 -> 0.17909064 | I21: =$G$21+($B$6-$G$21)*I16/Inputs!$C$24 -> 0.16696946 | J21: =$G$21+($B$6-$G$21)*J16/Inputs!$C$24 -> 0.15484828 | K21: =$G$21+($B$6-$G$21)*K16/Inputs!$C$24 -> 0.14272709 | L21: =$G$21+($B$6-$G$21)*L16/Inputs!$C$24 -> 0.13060591 | M21: =$G$21+($B$6-$G$21)*M16/Inputs!$C$24 -> 0.11848473 | N21: =$G$21+($B$6-$G$21)*N16/Inputs!$C$24 -> 0.10636355 | O21: =$G$21+($B$6-$G$21)*O16/Inputs!$C$24 -> 0.094242365 | ... Q21: =$G$21+($B$6-$G$21)*Q16/Inputs!$C$24 -> 0.07
A22: Residual income = NI - k x opening BV | C22: =C19-$B$5*C17 -> 808.97631 | D22: =D19-$B$5*D17 -> 1182.1512 | E22: =E19-$B$5*E17 -> 1495.6415 | F22: =F19-$B$5*F17 -> 1847.1023 | G22: =G19-$B$5*G17 -> 2177.9383 | H22: =H19-$B$5*H17 -> 2414.0864 | I22: =I19-$B$5*I17 -> 2633.8373 | J22: =J19-$B$5*J17 -> 2825.5224 | ... Q22: =Q19-$B$5*Q17 -> 2380.642
A23: Discount factor 1/(1+k)^t | C23: =1/(1+$B$5)^C15 -> 0.88230435 | D23: =1/(1+$B$5)^D15 -> 0.77846097 | E23: =1/(1+$B$5)^E15 -> 0.6868395 | F23: =1/(1+$B$5)^F15 -> 0.60600148 | G23: =1/(1+$B$5)^G15 -> 0.53467775 | H23: =1/(1+$B$5)^H15 -> 0.4717485 | I23: =1/(1+$B$5)^I15 -> 0.41622576 | J23: =1/(1+$B$5)^J15 -> 0.3672378 | ... Q23: =1/(1+$B$5)^Q15 -> 0.15285383
A24: PV of residual income | C24: =C22*C23 -> 713.76332 | D24: =D22*D23 -> 920.2586 | E24: =E22*E23 -> 1027.2656 | F24: =F22*F23 -> 1119.3467 | G24: =G22*G23 -> 1164.4951 | H24: =H22*H23 -> 1138.8416 | I24: =I22*I23 -> 1096.2709 | J24: =J22*J23 -> 1037.6386 | ... Q24: =Q22*Q23 -> 363.89025
A25: Implied payout in fade (1 - BV growth / ROE) | H25: =1-H21/H18 -> 0.026924064 | I25: =1-I21/I18 -> 0.073745393 | J25: =1-J21/J18 -> 0.12257397 | K25: =1-K21/K18 -> 0.17354169 | L25: =1-L21/L18 -> 0.22679228 | M25: =1-M21/M18 -> 0.28248263 | N25: =1-N21/N18 -> 0.34078434 | O25: =1-O21/O18 -> 0.40188549 | ... Q25: =1-Q21/Q18 -> 0.53333333
A26: Note: in the explicit stage, BV also changes with ESOP additions (non-income); RI uses Model PAT and opening BV. Fade stage assumes clean surplus.
A28: Residual income value
A29: Book value at 31-Mar-2026 | B29: =$B$8 -> 19973.522
A30: PV of RI - explicit FY27-FY31 | B30: =SUM(C24:G24) -> 4945.1294
A31: PV of RI - fade FY32-FY41 | B31: =SUM(H24:Q24) -> 7986.585
A32: Continuing value at FY41: (ROE_T - k) x BV_FY41 / (k - g) | B32: =($B$7-$B$5)*Q20/($B$5-$B$6) -> 40180.724
A33: PV of continuing value | B33: =B32*Q23 -> 6141.7777
A34: Equity value at 31-Mar-2026 | B34: =B29+B30+B31+B33 -> 39047.014
A35: Equity value at valuation date (rolled forward at k) | B35: =B34*(1+$B$5)^($B$9/365) -> 39845.408
A36: Value per diluted share (INR) | B36: =B35/$B$10 -> 526.63592
A37: Implied difference vs market price | B37: =B36/$B$11-1 -> -0.46518136
A38: Implied P/B on Mar-26 BV | B38: =B35/$B$8 -> 1.9949115
A39: Implied P/E on FY27E EPS | B39: =B36/Model!F85 -> 11.502383
A40: Share of value from continuing value | B40: =B33/B34 -> 0.15729186
A42: Justified P/B - ROE framework: P/B = (ROE - g) / (k - g)
A43: Sustainable ROE basis | B43: ROE | C43: P/B | D43: Value/share | E43: vs price
A44: FY26A reported ROE (14.2%) | B44: =Hist!H52 -> 0.142 | C44: =(B44-$B$6)/($B$5-$B$6) -> 1.1357229 | D44: =C44*$B$8/$B$10*(1+$B$5)^($B$9/365) -> 305.94945 | E44: =D44/$B$11-1 -> -0.68929679
A45: FY27E-FY31E average model ROE | B45: =AVERAGE(Model!F86:J86) -> 0.16806184 | C45: =(B45-$B$6)/($B$5-$B$6) -> 1.5468206 | D45: =C45*$B$8/$B$10*(1+$B$5)^($B$9/365) -> 416.69399 | E45: =D45/$B$11-1 -> -0.57683153
A46: Terminal ROE (Inputs) | B46: =$B$7 -> 0.15 | C46: =(B46-$B$6)/($B$5-$B$6) -> 1.2619143 | D46: =C46*$B$8/$B$10*(1+$B$5)^($B$9/365) -> 339.94384 | E46: =D46/$B$11-1 -> -0.65477421
A48: Market-implied expectations
A49: Market P/B on Mar-26 BV (price x diluted shares / BV) | B49: =$B$11*$B$10/$B$8 -> 3.7300709
A50: Implied sustainable ROE at k and g: g + P/B x (k - g) | B50: =$B$6+B49*($B$5-$B$6) -> 0.30647063
A51: Implied cost of equity at avg FY27-31 ROE and g: g + (ROE - g)/P/B | B51: =$B$6+(B45-$B$6)/B49 -> 0.096289538
A52: Market P/E on FY26 diluted EPS | B52: =$B$11/Hist!H73 -> 28.12625
A53: Market P/E on FY27E diluted EPS (model) | B53: =$B$11/Model!F85 -> 21.507072
A55: Peer cross-check (P/B applied to AU Mar-26 BVPS)
A56: Basis | B56: P/B | C56: Value/share | D56: vs price
A57: SFB median P/B | B57: =Peers!I20 -> 0.85382251 | C57: =B57*Model!E84 -> 227.91117 | D57: =C57/$B$11-1 -> -0.76854761
A58: Private-bank median P/B | B58: =Peers!I21 -> 1.312088 | C58: =B58*Model!E84 -> 350.23613 | D58: =C58/$B$11-1 -> -0.64432199
A59: All-peer median P/B | B59: =Peers!I22 -> 1.2899054 | C59: =B59*Model!E84 -> 344.31494 | D59: =C59/$B$11-1 -> -0.65033519
A60: Peer P/B-ROE regression at AU ROE | B60: =Peers!C30 -> 1.7692538 | C60: =B60*Model!E84 -> 472.26758 | D60: =C60/$B$11-1 -> -0.52039445
A62: Peer multiples are shown for context, not averaged mechanically: AU trades at a premium to every listed peer on P/B (see note for reasons).
A65: Sensitivity Analysis
A66: Residual-income value per share (INR): cost of equity (rows) x terminal ROE (columns); terminal g as Inputs
A67: CoE \ terminal ROE | B67: =B36 -> 526.63592 | C67: 0.13 | D67: 0.14 | E67: 0.15 | F67: 0.16 | G67: 0.17 | H67: 0.18 | I67: 0.19
B68: 0.115 | C68: 651.46562 | D68: 762.30365 | E68: 873.14168 | F68: 983.97972 | G68: 1094.8177 | H68: 1205.6558 | I68: 1316.4938
B69: 0.12 | C69: 560.34572 | D69: 655.94703 | E69: 751.54833 | F69: 847.14964 | G69: 942.75095 | H69: 1038.3523 | I69: 1133.9536
B70: 0.125 | C70: 486.94882 | D70: 570.26908 | E70: 653.58934 | F70: 736.9096 | G70: 820.22986 | H70: 903.55013 | I70: 986.87039
B71: 0.13 | C71: 426.78514 | D71: 500.03165 | E71: 573.27817 | F71: 646.52468 | G71: 719.7712 | H71: 793.01772 | I71: 866.26423
B72: =Inputs!C15 -> 0.13339575 | C72: 391.84934 | D72: 459.24263 | E72: 526.63592 | F72: 594.02921 | G72: 661.42249 | H72: 728.81578 | I72: 796.20907
B73: 0.135 | C73: 376.74973 | D73: 441.61223 | E73: 506.47473 | F73: 571.33722 | G73: 636.19972 | H73: 701.06222 | I73: 765.92472
B74: 0.14 | C74: 334.6277 | D74: 392.42667 | E74: 450.22565 | F74: 508.02463 | G74: 565.8236 | H74: 623.62258 | I74: 681.42156
B75: 0.145 | C75: 298.7973 | D75: 350.58289 | E75: 402.36849 | F75: 454.15408 | G75: 505.93967 | H75: 557.72526 | I75: 609.51086
A78: Residual-income value per share (INR): cost of equity (rows) x terminal growth (columns); terminal ROE as Inputs
A79: CoE \ terminal g | B79: =B36 -> 526.63592 | C79: 0.05 | D79: 0.06 | E79: 0.065 | F79: 0.07 | G79: 0.075 | H79: 0.08 | I79: 0.09
B80: 0.115 | C80: 751.24163 | D80: 801.24887 | E80: 833.63923 | F80: 873.14168 | G80: 922.42233 | H80: 985.67077 | I80: 1187.5877
B81: 0.12 | C81: 667.5198 | D81: 702.6447 | E81: 724.90473 | F81: 751.54833 | G81: 784.03596 | H81: 824.55831 | I81: 945.77216
B82: 0.125 | C82: 596.32947 | D82: 620.64682 | E82: 635.77063 | F82: 653.58934 | G82: 674.91085 | H82: 700.90211 | I82: 774.89588
B83: 0.13 | C83: 535.24983 | D83: 551.62261 | E83: 561.63784 | F83: 573.27817 | G83: 586.98635 | H83: 603.38223 | I83: 648.2661
B84: =Inputs!C15 -> 0.13339575 | C84: 498.5739 | D84: 510.7583 | E84: 518.13437 | F84: 526.63592 | G84: 536.55164 | H84: 548.27838 | I84: 579.66679
B85: 0.135 | C85: 482.43378 | D85: 492.91239 | E85: 499.22564 | F85: 506.47473 | G85: 514.89323 | H85: 524.7997 | I85: 551.05851
B86: 0.14 | C86: 436.44831 | D86: 442.52514 | E86: 446.13196 | F86: 450.22565 | G86: 454.91826 | H86: 460.35922 | I86: 474.3827
B87: 0.145 | C87: 396.16531 | D87: 398.94158 | E87: 400.55855 | F87: 402.36849 | G87: 404.41251 | H87: 406.74441 | I87: 412.58467

Sheet Hist
A1: Historical standalone financials, FY21-FY26 (INR crore unless stated)
A2: Reported figures in blue (converted from INR lakh /100). Calculated rows in black. FY25 not comparable (Fincare amalgamation, pooling). FY21 = regrouped comparative per FY22 filing.
A4: Line item | B4: Unit | C4: FY21 | D4: FY22 | E4: FY23 | F4: FY24 | G4: FY25 | H4: FY26 | I4: Source / note
A5: Income statement
A6: Interest/discount on advances | B6: Rs cr | C6: 3947.3625 | D6: 4881.5523 | E6: 6847.0183 | F6: 8442.1476 | G6: 13368.347 | H6: 15711.109 | I6: [S4] FY21-22, [S3] FY23-24, [S1] FY25-26; verified [S2][S5]
A7: Income on investments | B7: Rs cr | C7: 773.043 | D7: 780.532 | E7: 1189.8843 | F7: 1632.3875 | G7: 2238.176 | H7: 2647.2074 | I7: [S4] FY21-22, [S3] FY23-24, [S1] FY25-26; verified [S2][S5]
A8: Interest on RBI balances & inter-bank funds | B8: Rs cr | C8: 85.0066 | D8: 87.0812 | E8: 58.2772 | F8: 66.8798 | G8: 69.1482 | H8: 92.5533 | I8: [S4] FY21-22, [S3] FY23-24, [S1] FY25-26; verified [S2][S5]
A9: Other interest | B9: Rs cr | C9: 144.6394 | D9: 172.5652 | E9: 110.2285 | F9: 413.2982 | G9: 388.0596 | H9: 185.469 | I9: [S4] FY21-22, [S3] FY23-24, [S1] FY25-26; verified [S2][S5]
A10: Interest earned | B10: Rs cr | C10: =SUM(C6:C9) -> 4950.0515 | D10: =SUM(D6:D9) -> 5921.7307 | E10: =SUM(E6:E9) -> 8205.4083 | F10: =SUM(F6:F9) -> 10554.713 | G10: =SUM(G6:G9) -> 16063.731 | H10: =SUM(H6:H9) -> 18636.339 | I10: Calc; ties to reported (Checks)
A11: Interest expended | B11: Rs cr | C11: 2584.6097 | D11: 2687.6058 | E11: 3780.1264 | F11: 5397.6293 | G11: 8052.1494 | H11: 9523.6562 | I11: [S4] FY21-22, [S3] FY23-24, [S1] FY25-26; verified [S2][S5]; FY24 per XBRL
A12: Net interest income (NII) | B12: Rs cr | C12: =C10-C11 -> 2365.4418 | D12: =D10-D11 -> 3234.1249 | E12: =E10-E11 -> 4425.2819 | F12: =F10-F11 -> 5157.0838 | G12: =G10-G11 -> 8011.5815 | H12: =H10-H11 -> 9112.6828 | I12: Calc
A13: Other income | B13: Rs cr | C13: 1420.9327 | D13: 993.6942 | E13: 1034.4642 | F13: 1745.8928 | G13: 2526.3111 | H13: 2977.9386 | I13: [S4] FY21-22, [S3] FY23-24, [S1] FY25-26; verified [S2][S5]. FY21 includes Aavas stake-sale gain (co. presentation) - one-off
A14: Net total income | B14: Rs cr | C14: =C12+C13 -> 3786.3745 | D14: =D12+D13 -> 4227.8191 | E14: =E12+E13 -> 5459.7461 | F14: =F12+F13 -> 6902.9766 | G14: =G12+G13 -> 10537.893 | H14: =H12+H13 -> 12090.621 | I14: Calc
A15: Employee cost | B15: Rs cr | C15: 980.1731 | D15: 1378.9217 | E15: 1793.0283 | F15: 2103.6806 | G15: 3147.7604 | H15: 3848.1619 | I15: [S4] FY21-22, [S3] FY23-24, [S1] FY25-26; verified [S2][S5]
A16: Other operating expenses | B16: Rs cr | C16: 678.2521 | D16: 1033.8526 | E16: 1647.2416 | F16: 2284.3216 | G16: 2809.4549 | H16: 3153.6996 | I16: [S4] FY21-22, [S3] FY23-24, [S1] FY25-26; verified [S2][S5]
A17: Operating expenses | B17: Rs cr | C17: =C15+C16 -> 1658.4252 | D17: =D15+D16 -> 2412.7743 | E17: =E15+E16 -> 3440.2699 | F17: =F15+F16 -> 4388.0022 | G17: =G15+G16 -> 5957.2153 | H17: =H15+H16 -> 7001.8615 | I17: Calc
A18: Pre-provision operating profit (PPOP) | B18: Rs cr | C18: =C14-C17 -> 2127.9493 | D18: =D14-D17 -> 1815.0448 | E18: =E14-E17 -> 2019.4762 | F18: =F14-F17 -> 2514.9744 | G18: =G14-G17 -> 4580.6773 | H18: =H14-H17 -> 5088.7599 | I18: Calc
A19: Provisions & contingencies (ex tax) | B19: Rs cr | C19: 669.4411 | D19: 360.9743 | E19: 154.8394 | F19: 438.7439 | G19: 1792.6232 | H19: 1614.7143 | I19: [S4] FY21-22, [S3] FY23-24, [S1] FY25-26; verified [S2][S5]
A20: Exceptional items (expense) | B20: Rs cr | C20: 0 | D20: 0 | E20: 0 | F20: 76.8014 | G20: 0 | H20: 0 | I20: FY24: Fincare merger expenses Rs76.8 cr [S3][S5]
A21: Profit before tax | B21: Rs cr | C21: =C18-C19-C20 -> 1458.5082 | D21: =D18-D19-D20 -> 1454.0705 | E21: =E18-E19-E20 -> 1864.6368 | F21: =F18-F19-F20 -> 1999.4291 | G21: =G18-G19-G20 -> 2788.0541 | H21: =H18-H19-H20 -> 3474.0456 | I21: Calc
A22: Tax expense | B22: Rs cr | C22: 287.8236 | D22: 324.2362 | E22: 436.7115 | F22: 464.7101 | G22: 682.1275 | H22: 832.7913 | I22: [S4] FY21-22, [S3] FY23-24, [S1] FY25-26; verified [S2][S5]
A23: Net profit (PAT) | B23: Rs cr | C23: =C21-C22 -> 1170.6846 | D23: =D21-D22 -> 1129.8343 | E23: =E21-E22 -> 1427.9253 | F23: =F21-F22 -> 1534.719 | G23: =G21-G22 -> 2105.9266 | H23: =H21-H22 -> 2641.2543 | I23: Calc; ties to reported PAT (Checks)
A24: Net profit as reported | B24: Rs cr | C24: 1170.6846 | D24: 1129.8342 | E24: 1427.9253 | F24: 1534.719 | G24: 2105.9266 | H24: 2641.2543 | I24: [S4] FY21-22, [S3] FY23-24, [S1] FY25-26; verified [S2][S5]
A25: Interest earned as reported | B25: Rs cr | C25: 4950.0515 | D25: 5921.7307 | E25: 8205.4083 | F25: 10554.713 | G25: 16063.731 | H25: 18636.339 | I25: [S4] FY21-22, [S3] FY23-24, [S1] FY25-26; verified [S2][S5]
A26: PBT as reported | B26: Rs cr | C26: 1458.5082 | D26: 1454.0705 | E26: 1864.6368 | F26: 1999.4291 | G26: 2788.0541 | H26: 3474.0456 | I26: [S4] FY21-22, [S3] FY23-24, [S1] FY25-26; verified [S2][S5]
A28: Balance sheet (31 March)
A29: Cash & balances with RBI | B29: Rs cr | C29: 1569.3478 | D29: 2468.4072 | E29: 8916.093 | F29: 4638.0094 | G29: 8604.6221 | H29: 6973.2602 | I29: [S4] FY21-22, [S3] FY23-24, [S1] FY25-26
A30: Balances with banks & money at call | B30: Rs cr | C30: 3211.9877 | D30: 3460.1078 | E30: 509.0793 | F30: 1738.3249 | G30: 861.7397 | H30: 1550.1495 | I30: [S4] FY21-22, [S3] FY23-24, [S1] FY25-26
A31: Investments | B31: Rs cr | C31: 10815.414 | D31: 15306.504 | E31: 20072.01 | F31: 27133.365 | G31: 37847.524 | H31: 44793.651 | I31: [S4] FY21-22, [S3] FY23-24, [S1] FY25-26
A32: Advances (net) | B32: Rs cr | C32: 34608.914 | D32: 46095.256 | E32: 58421.544 | F32: 73162.655 | G32: 107092.48 | H32: 134275.63 | I32: [S4] FY21-22, [S3] FY23-24, [S1] FY25-26
A33: Fixed assets | B33: Rs cr | C33: 482.3685 | D33: 622.5713 | E33: 740.1394 | F33: 851.5924 | G33: 912.4652 | H33: 1436.382 | I33: [S4] FY21-22, [S3] FY23-24, [S1] FY25-26
A34: Other assets | B34: Rs cr | C34: 903.2738 | D34: 1124.9534 | E34: 1557.2527 | F34: 1901.7232 | G34: 2526.8312 | H34: 2768.3941 | I34: [S4] FY21-22, [S3] FY23-24, [S1] FY25-26
A35: Total assets | B35: Rs cr | C35: =SUM(C29:C34) -> 51591.306 | D35: =SUM(D29:D34) -> 69077.8 | E35: =SUM(E29:E34) -> 90216.118 | F35: =SUM(F29:F34) -> 109425.67 | G35: =SUM(G29:G34) -> 157845.67 | H35: =SUM(H29:H34) -> 191797.47 | I35: Calc
A36: Share capital (face value INR10) | B36: Rs cr | C36: 312.2134 | D36: 314.9 | E36: 666.745 | F36: 669.1625 | G36: 744.5305 | H36: 748.2671 | I36: [S4] FY21-22, [S3] FY23-24, [S1] FY25-26
A37: Employee stock options outstanding | B37: Rs cr | C37: 103.1171 | D37: 41.3316 | E37: 44.0252 | F37: 62.7256 | G37: 124.235 | H37: 240.7582 | I37: [S4] FY21-22, [S3] FY23-24, [S1] FY25-26
A38: Reserves & surplus | B38: Rs cr | C38: 5859.8853 | D38: 7157.7824 | E38: 10266.574 | F38: 11827.643 | G38: 16297.516 | H38: 18984.497 | I38: [S4] FY21-22, [S3] FY23-24, [S1] FY25-26
A39: Shareholders' funds (net worth incl. ESOP o/s) | B39: Rs cr | C39: =SUM(C36:C38) -> 6275.2158 | D39: =SUM(D36:D38) -> 7514.014 | E39: =SUM(E36:E38) -> 10977.344 | F39: =SUM(F36:F38) -> 12559.532 | G39: =SUM(G36:G38) -> 17166.282 | H39: =SUM(H36:H38) -> 19973.522 | I39: Calc; FY26 = Rs19,974 cr = co. shareholders funds [S9]
A40: Deposits | B40: Rs cr | C40: 35979.314 | D40: 52584.621 | E40: 69364.986 | F40: 87182.116 | G40: 124268.54 | H40: 152661.16 | I40: [S4] FY21-22, [S3] FY23-24, [S1] FY25-26
A41: Borrowings | B41: Rs cr | C41: 7029.6957 | D41: 5990.7786 | E41: 6298.6521 | F41: 5479.3721 | G41: 11659.902 | H41: 13871.545 | I41: [S4] FY21-22, [S3] FY23-24, [S1] FY25-26
A42: Other liabilities & provisions | B42: Rs cr | C42: 2307.0802 | D42: 2988.3872 | E42: 3575.1362 | F42: 4204.6499 | G42: 4750.9383 | H42: 5291.2379 | I42: [S4] FY21-22, [S3] FY23-24, [S1] FY25-26
A43: Total liabilities & equity | B43: Rs cr | C43: =C39+SUM(C40:C42) -> 51591.306 | D43: =D39+SUM(D40:D42) -> 69077.8 | E43: =E39+SUM(E40:E42) -> 90216.118 | F43: =F39+SUM(F40:F42) -> 109425.67 | G43: =G39+SUM(G40:G42) -> 157845.67 | H43: =H39+SUM(H40:H42) -> 191797.47 | I43: Calc
A44: Total as reported | B44: Rs cr | C44: 51591.306 | D44: 69077.8 | E44: 90216.118 | F44: 109425.67 | G44: 157845.67 | H44: 191797.47 | I44: [S4] FY21-22, [S3] FY23-24, [S1] FY25-26
A46: Operating data (company presentations - see confidence in Sources)
A47: Gross loan portfolio (GLP, incl. off-book) | B47: Rs cr | C47: n/a | D47: n/a | E47: n/a | F47: 73999 | G47: 115704 | H47: 140327 | I47: [S11] Mar-24 segment table sum; [S8] Mar-25, Mar-26
A48: CASA deposits | B48: Rs cr | C48: n/a | D48: n/a | E48: 26660 | F48: 29126 | G48: n/a | H48: 43357 | I48: [S11] FY23-24; [S9] FY26. FY25 not captured (co. states CASA +20% YoY -> ~36,100)
A49: CASA ratio (reported) | B49: % | C49: 0.23 | D49: 0.37 | E49: 0.38 | F49: 0.33 | G49: 0.29 | H49: 0.28 | I49: [S12] FY21-22; [S11] FY23-24; [S8] FY25; [S9] FY26
A50: NIM (reported, company definition) | B50: % | C50: n/a | D50: n/a | E50: 0.061 | F50: n/a | G50: 0.0594 | H50: 0.0565 | I50: [S11] FY23; [S8] FY25-26
A51: Cost of funds (reported) | B51: % | C51: n/a | D51: n/a | E51: 0.0596 | F51: 0.068 | G51: 0.0707 | H51: 0.0675 | I51: [S11] FY23-24; [S8] FY25-26
A52: ROE (reported) | B52: % | C52: 0.12 | D52: 0.164 | E52: 0.154 | F52: 0.135 | G52: 0.131 | H52: 0.142 | I52: [S8] multi-year slide; FY26 14.2% also [S9]
A54: Regulatory capital (Basel II, SFB framework)
A55: Tier 1 capital (= CET1; no AT1) | B55: Rs cr | C55: n/a | D55: 7171.7024 | E55: 10568.909 | F55: 11972.37 | G55: 16339.278 | H55: 19590.83 | I55: [S7] FY22-25; [S6] FY26
A56: Tier 2 capital | B56: Rs cr | C56: n/a | D56: 472.3841 | E56: 878.6168 | F56: 800.8048 | G56: 1726.264 | H56: 2117.74 | I56: [S7][S6]
A57: Risk-weighted assets (credit risk only for SFBs) | B57: Rs cr | C57: n/a | D57: 36416.689 | E57: 48519.301 | F57: 63684.831 | G57: 90072.234 | H57: 116233.98 | I57: [S7][S6]
A58: CRAR (calculated) | B58: % | C58: n/a | D58: =(D55+D56)/D57 -> 0.20990614 | E58: =(E55+E56)/E57 -> 0.23593757 | F58: =(F55+F56)/F57 -> 0.20056856 | G58: =(G55+G56)/G57 -> 0.20056727 | H58: =(H55+H56)/H57 -> 0.18676612 | I58: Calc
A59: Tier 1 / CET1 ratio (calculated) | B59: % | C59: n/a | D59: =D55/D57 -> 0.1969345 | E59: =E55/E57 -> 0.21782897 | F59: =F55/F57 -> 0.18799406 | G59: =G55/G57 -> 0.18140194 | H59: =H55/H57 -> 0.1685465 | I59: Calc; FY26 16.86% = reported CET1 [S2]
A60: CRAR (reported in results) | B60: % | C60: 0.2337 | D60: 0.2099 | E60: 0.2359 | F60: 0.2006 | G60: 0.2006 | H60: 0.1868 | I60: [S4][S3][S1]
A61: RWA / total assets | B61: % | C61: n/a | D61: =D57/D35 -> 0.52718368 | E61: =E57/E35 -> 0.53781189 | F61: =F57/F35 -> 0.58199169 | G61: =G57/G35 -> 0.57063483 | H61: =H57/H35 -> 0.60602458 | I61: Calc
A63: Calculated ratios (model definitions; see DataDict)
A64: Growth in net advances | B64: % | C64: n/a | D64: =D32/C32-1 -> 0.3318897 | E64: =E32/D32-1 -> 0.26740903 | F64: =F32/E32-1 -> 0.25232319 | G64: =G32/F32-1 -> 0.46375887 | H64: =H32/G32-1 -> 0.2538287 | I64: FY25 inflated by amalgamation
A65: Growth in deposits | B65: % | C65: n/a | D65: =D40/C40-1 -> 0.46152371 | E65: =E40/D40-1 -> 0.31911166 | F65: =F40/E40-1 -> 0.25686057 | G65: =G40/F40-1 -> 0.42539031 | H65: =H40/G40-1 -> 0.22847793 | I65: FY25 inflated by amalgamation
A66: Yield on avg net advances | B66: % | C66: n/a | D66: =D6/((D32+C32)/2) -> 0.12097398 | E66: =E6/((E32+D32)/2) -> 0.13102235 | F66: =F6/((F32+E32)/2) -> 0.12831552 | G66: =G6/((G32+F32)/2) -> 0.14832695 | H66: =H6/((H32+G32)/2) -> 0.1301838
A67: Cost of funds on avg (deposits + borrowings) | B67: % | C67: n/a | D67: =D11/((D40+D41+C40+C41)/2) -> 0.052913746 | E67: =E11/((E40+E41+D40+D41)/2) -> 0.056319331 | F67: =F11/((F40+F41+E40+E41)/2) -> 0.064133376 | G67: =G11/((G40+G41+F40+F41)/2) -> 0.070450603 | H67: =H11/((H40+H41+G40+G41)/2) -> 0.062974409
A68: NIM: NII / avg interest-earning assets (adv+inv+cash+bank) | B68: % | C68: n/a | D68: =D12/((SUM(D29:D32)+SUM(C29:C32))/2) -> 0.055032102 | E68: =E12/((SUM(E29:E32)+SUM(D29:D32))/2) -> 0.057008829 | F68: =F12/((SUM(F29:F32)+SUM(E29:E32))/2) -> 0.053004318 | G68: =G12/((SUM(G29:G32)+SUM(F29:F32))/2) -> 0.061372918 | H68: =H12/((SUM(H29:H32)+SUM(G29:G32))/2) -> 0.053290689 | I68: Model def. (co. uses daily avg incl. off-book)
A69: Cost-to-income (opex / net total income) | B69: % | C69: =C17/C14 -> 0.4379982 | D69: =D17/D14 -> 0.57069005 | E69: =E17/E14 -> 0.63011536 | F69: =F17/F14 -> 0.63566813 | G69: =G17/G14 -> 0.56531372 | H69: =H17/H14 -> 0.57911511
A70: Opex / avg total assets | B70: % | C70: n/a | D70: =D17/((D35+C35)/2) -> 0.039989926 | E70: =E17/((E35+D35)/2) -> 0.043193989 | F70: =F17/((F35+E35)/2) -> 0.043958755 | G70: =G17/((G35+F35)/2) -> 0.044578034 | H70: =H17/((H35+G35)/2) -> 0.040051474
A71: Credit cost: provisions / avg net advances | B71: % | C71: n/a | D71: =D19/((D32+C32)/2) -> 0.008945617 | E71: =E19/((E32+D32)/2) -> 0.0029629571 | F71: =F19/((F32+E32)/2) -> 0.0066686411 | G71: =G19/((G32+F32)/2) -> 0.019889843 | H71: =H19/((H32+G32)/2) -> 0.013379682
A72: EPS basic (as reported) | B72: INR | C72: 38.19 | D72: 36.06 | E72: 21.86 | F72: 22.98 | G72: 28.32 | H72: 35.4 | I72: FY21-22 pre 1:1 bonus [S4]
A73: EPS diluted (as reported) | B73: INR | C73: 37.86 | D73: 35.69 | E73: 21.74 | F73: 22.86 | G73: 28.24 | H73: 35.01
A74: Bonus adjustment factor | B74: x | C74: 0.5 | D74: 0.5 | E74: 1 | F74: 1 | G74: 1 | H74: 1 | I74: 1:1 bonus approved with FY22 results [S4]
A75: EPS diluted, bonus-adjusted | B75: INR | C75: =C73*C74 -> 18.93 | D75: =D73*D74 -> 17.845 | E75: =E73*E74 -> 21.74 | F75: =F73*F74 -> 22.86 | G75: =G73*G74 -> 28.24 | H75: =H73*H74 -> 35.01 | I75: Calc
A76: Gross NPA | B76: Rs cr | C76: 1502.8291 | D76: 924.3782 | E76: 981.3126 | F76: 1237.4004 | G76: 2477.0299 | H76: 2755.6406 | I76: [S4][S3][S1]
A77: Net NPA | B77: Rs cr | C77: 755.4547 | D77: 230.8455 | E77: 245.1588 | F77: 400.9897 | G77: 791.3432 | H77: 989.8987 | I77: [S4][S3][S1]
A78: GNPA ratio (reported) | B78: % | C78: 0.0425 | D78: 0.0198 | E78: 0.0166 | F78: 0.0167 | G78: 0.0228 | H78: 0.0203 | I78: [S4][S3][S1]
A79: NNPA ratio (reported) | B79: % | C79: 0.0218 | D79: 0.005 | E79: 0.0042 | F79: 0.0055 | G79: 0.0074 | H79: 0.0074 | I79: [S4][S3][S1]
A80: Specific PCR (1 - NNPA/GNPA) | B80: % | C80: =1-C77/C76 -> 0.49731164 | D80: =1-D77/D76 -> 0.75026942 | E80: =1-E77/E76 -> 0.75017257 | F80: =1-F77/F76 -> 0.67594184 | G80: =1-G77/G76 -> 0.68052739 | H80: =1-H77/H76 -> 0.64077366 | I80: Calc (excl. technical write-offs)
A81: ROA: PAT / avg total assets | B81: % | C81: n/a | D81: =D23/((D35+C35)/2) -> 0.018726157 | E81: =E23/((E35+D35)/2) -> 0.017928183 | F81: =F23/((F35+E35)/2) -> 0.015374727 | G81: =G23/((G35+F35)/2) -> 0.015758716 | H81: =H23/((H35+G35)/2) -> 0.015108286 | I81: Model def.; co. reports 1.57% FY26 on its averaging
A82: ROE: PAT / avg shareholders funds | B82: % | C82: n/a | D82: =D23/((D39+C39)/2) -> 0.163872 | E82: =E23/((E39+D39)/2) -> 0.15444245 | F82: =F23/((F39+E39)/2) -> 0.13040975 | G82: =G23/((G39+F39)/2) -> 0.14169009 | H82: =H23/((H39+G39)/2) -> 0.14223308 | I82: FY25 overstated: opening equity excludes Fincare (pooling)
A83: Leverage: total assets / equity | B83: x | C83: =C35/C39 -> 8.2214393 | D83: =D35/D39 -> 9.1931956 | E83: =E35/E39 -> 8.2183924 | F83: =F35/F39 -> 8.7125599 | G83: =G35/G39 -> 9.1950994 | H83: =H35/H39 -> 9.6025863
A84: Net advances / deposits | B84: % | C84: =C32/C40 -> 0.96191145 | D84: =D32/D40 -> 0.87659197 | E84: =E32/E40 -> 0.84223392 | F84: =F32/F40 -> 0.83919338 | G84: =G32/G40 -> 0.86178273 | H84: =H32/H40 -> 0.87956641
A85: Book value per share | B85: INR | C85: =C39/(C36/10) -> 200.99124 | D85: =D39/(D36/10) -> 238.61588 | E85: =E39/(E36/10) -> 164.64081 | F85: =F39/(F36/10) -> 187.69031 | G85: =G39/(G36/10) -> 230.56519 | H85: =H39/(H36/10) -> 266.93038 | I85: FY21-22 pre-bonus share count
A86: Equity roll-forward: other movements (issuance, merger, ESOP, dividends paid, reserves) | B86: Rs cr | C86: n/a | D86: =D39-C39-D23 -> 108.9639 | E86: =E39-D39-E23 -> 2035.4044 | F86: =F39-E39-F23 -> 47.4688 | G86: =G39-F39-G23 -> 2500.8236 | H86: =H39-G39-H23 -> 165.986 | I86: Calc residual (closing - opening - PAT)

Sheet Peers
A1: Peer Comparison - FY26 Audited Standalone (NSE XBRL [S17]); prices 29-May-2026 [S15]; INR crore unless stated
A2: Book value = share capital + reserves & surplus (incl. ESOP o/s where tagged); not tangible BV. ROE = FY26 PAT / avg (Mar-25, Mar-26) equity. NII/assets = (interest earned - expended) / avg total assets.
T3: Raw XBRL values (INR crore = rupees / 1e7; ratios as filed) [S17]
A4: Bank | B4: Symbol | C4: Group | D4: Price (INR) | E4: Shares (cr) | F4: Mkt cap | G4: Book value | H4: FY26 PAT | I4: P/B | J4: P/E | K4: ROE | L4: ROA (rep.) | M4: NII/avg assets | N4: GNPA % | O4: NNPA % | P4: CET1 % | Q4: Adv growth | R4: Dep growth | S4: In regr. | T4: PaidUp (Rs) | U4: Face value | V4: Capital Mar26 | W4: Reserves Mar26 | X4: Capital Mar25 | Y4: Reserves Mar25 | Z4: PAT FY26 | AA4: Int earned | AB4: Int expended | AC4: Assets Mar26 | AD4: Assets Mar25 | AE4: Adv Mar26 | AF4: Adv Mar25 | AG4: Dep Mar26 | AH4: Dep Mar25 | AI4: GNPA% | AJ4: NNPA% | AK4: CET1 | AL4: ROA | AN4: Regr ROE | AO4: Regr P/B | AP4: P/E if num
A5: AU Small Finance Bank | B5: AUBANK | C5: Subject | D5: 984.7 | E5: =T5/U5 -> 74.827 | F5: =D5*E5 -> 73682.147 | G5: =V5+W5 -> 19973.52 | H5: =Z5 -> 2641.25 | I5: =F5/G5 -> 3.6889916 | J5: =IF(H5>0,F5/H5,"n.m.") -> 27.896695 | K5: =H5/((V5+W5+X5+Y5)/2) -> 0.14223286 | L5: =AL5 -> 0.0157 | M5: =(AA5-AB5)/((AC5+AD5)/2) -> 0.052125604 | N5: =AI5 -> 0.0203 | O5: =AJ5 -> 0.0074 | P5: =AK5 -> 0.1686 | Q5: =AE5/AF5-1 -> 0.25382875 | R5: =AG5/AH5-1 -> 0.22847794 | T5: 748.27 | U5: 10 | V5: 748.27 | W5: 19225.25 | X5: 744.53 | Y5: 16421.75 | Z5: 2641.25 | AA5: 18636.34 | AB5: 9523.66 | AC5: 191797.47 | AD5: 157845.67 | AE5: 134275.63 | AF5: 107092.48 | AG5: 152661.16 | AH5: 124268.54 | AI5: 0.0203 | AJ5: 0.0074 | AK5: 0.1686 | AL5: 0.0157 | AP5: =IF(ISNUMBER(J5),J5,"") -> 27.896695
A6: Equitas SFB | B6: EQUITASBNK | C6: SFB | D6: 70.21 | E6: =T6/U6 -> 114.104 | F6: =D6*E6 -> 8011.2418 | G6: =V6+W6 -> 6124.83 | H6: =Z6 -> 103.08 | I6: =F6/G6 -> 1.3079942 | J6: =IF(H6>0,F6/H6,"n.m.") -> 77.718683 | K6: =H6/((V6+W6+X6+Y6)/2) -> 0.016902032 | L6: =AL6 -> 0.0018 | M6: =(AA6-AB6)/((AC6+AD6)/2) -> 0.059784749 | N6: =AI6 -> 0.026 | O6: =AJ6 -> 0.0072 | P6: =AK6 -> 0.1668 | Q6: =AE6/AF6-1 -> 0.18068491 | R6: =AG6/AH6-1 -> 0.079485751 | S6: =IF(K6>0.05,1,0) -> 0 | T6: 1141.04 | U6: 10 | V6: 1141.04 | W6: 4983.79 | X6: 1139.86 | Y6: 4932.66 | Z6: 103.08 | AA6: 6794.24 | AB6: 3403.07 | AC6: 60610.36 | AD6: 52835.63 | AE6: 42751.29 | AF6: 36208.89 | AG6: 46533.09 | AH6: 43106.72 | AI6: 0.026 | AJ6: 0.0072 | AK6: 0.1668 | AL6: 0.0018 | AN6: =IF(S6=1,K6,"") | AO6: =IF(S6=1,I6,"") | AP6: =IF(ISNUMBER(J6),J6,"") -> 77.718683
A7: Ujjivan SFB | B7: UJJIVANSFB | C7: SFB | D7: 54.39 | E7: =T7/U7 -> 194.271 | F7: =D7*E7 -> 10566.4 | G7: =V7+W7 -> 6815.68 | H7: =Z7 -> 692.63 | I7: =F7/G7 -> 1.5503075 | J7: =IF(H7>0,F7/H7,"n.m.") -> 15.255475 | K7: =H7/((V7+W7+X7+Y7)/2) -> 0.10739216 | L7: =AL7 -> 0.0137 | M7: =(AA7-AB7)/((AC7+AD7)/2) -> 0.073571924 | N7: =AI7 -> 0.0226 | O7: =AJ7 -> 0.0043 | P7: =AK7 -> 0.197 | Q7: =AE7/AF7-1 -> 0.26666295 | R7: =AG7/AH7-1 -> 0.21359945 | S7: =IF(K7>0.05,1,0) -> 1 | T7: 1942.71 | U7: 10 | V7: 1942.71 | W7: 4872.97 | X7: 1935 | Y7: 4148.4 | Z7: 692.63 | AA7: 6931.45 | AB7: 3060.45 | AC7: 57541.21 | AD7: 47689.15 | AE7: 39760.55 | AF7: 31390 | AG7: 45668.33 | AH7: 37630.48 | AI7: 0.0226 | AJ7: 0.0043 | AK7: 0.197 | AL7: 0.0137 | AN7: =IF(S7=1,K7,"") -> 0.10739216 | AO7: =IF(S7=1,I7,"") -> 1.5503075 | AP7: =IF(ISNUMBER(J7),J7,"") -> 15.255475
A8: Jana SFB | B8: JSFB | C8: SFB | D8: 495.25 | E8: =T8/U8 -> 10.532 | F8: =D8*E8 -> 5215.973 | G8: =V8+W8 -> 4470.2 | H8: =Z8 -> 326.43 | I8: =F8/G8 -> 1.1668321 | J8: =IF(H8>0,F8/H8,"n.m.") -> 15.978841 | K8: =H8/((V8+W8+X8+Y8)/2) -> 0.07601516 | L8: =AL8 -> 0.0126 | M8: =(AA8-AB8)/((AC8+AD8)/2) -> 0.060367577 | N8: =AI8 -> 0.0246 | O8: =AJ8 -> 0.0092 | P8: =AK8 -> 0.1751 | Q8: =AE8/AF8-1 -> 0.245704 | R8: =AG8/AH8-1 -> 0.22887226 | S8: =IF(K8>0.05,1,0) -> 1 | T8: 105.32 | U8: 10 | V8: 105.32 | W8: 4364.88 | X8: 105.06 | Y8: 4013.29 | Z8: 326.43 | AA8: 5352.87 | AB8: 2759.74 | AC8: 47447.73 | AD8: 38463.62 | AE8: 33827.69 | AF8: 27155.48 | AG8: 35784.49 | AH8: 29119.78 | AI8: 0.0246 | AJ8: 0.0092 | AK8: 0.1751 | AL8: 0.0126 | AN8: =IF(S8=1,K8,"") -> 0.07601516 | AO8: =IF(S8=1,I8,"") -> 1.1668321 | AP8: =IF(ISNUMBER(J8),J8,"") -> 15.978841
A9: Capital SFB | B9: CAPITALSFB | C9: SFB | D9: 274.65 | E9: =T9/U9 -> 4.542 | F9: =D9*E9 -> 1247.4603 | G9: =V9+W9 -> 1461.03 | H9: =Z9 -> 141.39 | I9: =F9/G9 -> 0.85382251 | J9: =IF(H9>0,F9/H9,"n.m.") -> 8.8228326 | K9: =H9/((V9+W9+X9+Y9)/2) -> 0.10095067 | L9: =AL9 -> 0.0123 | M9: =(AA9-AB9)/((AC9+AD9)/2) -> 0.041473252 | N9: =AI9 -> 0.0254 | O9: =AJ9 -> 0.0124 | P9: =AK9 -> 0.1958 | Q9: =AE9/AF9-1 -> 0.20901812 | R9: =AG9/AH9-1 -> 0.20366832 | S9: =IF(K9>0.05,1,0) -> 1 | T9: 45.42 | U9: 10 | V9: 45.42 | W9: 1415.61 | X9: 45.25 | Y9: 1294.89 | Z9: 141.39 | AA9: 1048.6 | AB9: 587.18 | AC9: 12143.94 | AD9: 10107.51 | AE9: 8572.41 | AF9: 7090.39 | AG9: 10017.65 | AH9: 8322.6 | AI9: 0.0254 | AJ9: 0.0124 | AK9: 0.1958 | AL9: 0.0123 | AN9: =IF(S9=1,K9,"") -> 0.10095067 | AO9: =IF(S9=1,I9,"") -> 0.85382251 | AP9: =IF(ISNUMBER(J9),J9,"") -> 8.8228326
A10: Suryoday SFB | B10: SURYODAY | C10: SFB | D10: 163.59 | E10: =T10/U10 -> 10.629 | F10: =D10*E10 -> 1738.7981 | G10: =V10+W10 -> 2078.32 | H10: =Z10 -> 151.97 | I10: =F10/G10 -> 0.83663637 | J10: =IF(H10>0,F10/H10,"n.m.") -> 11.441719 | K10: =H10/((V10+W10+X10+Y10)/2) -> 0.075882369 | L10: =AL10 -> 0.0089 | M10: =(AA10-AB10)/((AC10+AD10)/2) -> 0.061902032 | N10: =AI10 -> 0.0655 | O10: =AJ10 -> 0.0421 | P10: =AK10 -> 0.1959 | Q10: =AE10/AF10-1 -> 0.2911879 | R10: =AG10/AH10-1 -> 0.32273685 | S10: =IF(K10>0.05,1,0) -> 1 | T10: 106.29 | U10: 10 | V10: 106.29 | W10: 1972.03 | X10: 106.28 | Y10: 1820.81 | Z10: 151.97 | AA10: 2160.29 | AB10: 1061.58 | AC10: 19883.96 | AD10: 15614.39 | AE10: 12878.76 | AF10: 9974.35 | AG10: 13994.04 | AH10: 10579.61 | AI10: 0.0655 | AJ10: 0.0421 | AK10: 0.1959 | AL10: 0.0089 | AN10: =IF(S10=1,K10,"") -> 0.075882369 | AO10: =IF(S10=1,I10,"") -> 0.83663637 | AP10: =IF(ISNUMBER(J10),J10,"") -> 11.441719
A11: ESAF SFB | B11: ESAFSFB | C11: SFB | D11: 28.61 | E11: =T11/U11 -> 51.566 | F11: =D11*E11 -> 1475.3033 | G11: =V11+W11 -> 1780.04 | H11: =Z11 -> -166.4 | I11: =F11/G11 -> 0.82880343 | J11: =IF(H11>0,F11/H11,"n.m.") -> n.m. | K11: =H11/((V11+W11+X11+Y11)/2) -> -0.089341083 | L11: =AL11 -> -0.006 | M11: =(AA11-AB11)/((AC11+AD11)/2) -> 0.086509951 | N11: =AI11 -> 0.0541 | O11: =AJ11 -> 0.0177 | P11: =AK11 -> 0.1423 | Q11: =AE11/AF11-1 -> 0.19782426 | R11: =AG11/AH11-1 -> 0.11057189 | S11: =IF(K11>0.05,1,0) -> 0 | T11: 515.66 | U11: 10 | V11: 515.66 | W11: 1264.38 | X11: 515.43 | Y11: 1429.58 | Z11: -166.4 | AA11: 4348.23 | AB11: 1837.44 | AC11: 30867.98 | AD11: 27178.29 | AE11: 21594.22 | AF11: 18027.87 | AG11: 25850.16 | AH11: 23276.44 | AI11: 0.0541 | AJ11: 0.0177 | AK11: 0.1423 | AL11: -0.006 | AN11: =IF(S11=1,K11,"") | AO11: =IF(S11=1,I11,"") | AP11: =IF(ISNUMBER(J11),J11,"")
A12: Utkarsh SFB | B12: UTKARSHBNK | C12: SFB | D12: 13.26 | E12: =T12/U12 -> 177.952 | F12: =D12*E12 -> 2359.6435 | G12: =V12+W12 -> 2775.6 | H12: =Z12 -> -1150.98 | I12: =F12/G12 -> 0.85013818 | J12: =IF(H12>0,F12/H12,"n.m.") -> n.m. | K12: =H12/((V12+W12+X12+Y12)/2) -> -0.40033391 | L12: =AL12 -> -0.0416 | M12: =(AA12-AB12)/((AC12+AD12)/2) -> 0.051818611 | N12: =AI12 -> 0.0771 | O12: =AJ12 -> 0.0329 | P12: =AK12 -> 0.1498 | Q12: =AE12/AF12-1 -> -0.034562589 | R12: =AG12/AH12-1 -> 0.0040935374 | S12: =IF(K12>0.05,1,0) -> 0 | T12: 1779.52 | U12: 10 | V12: 1779.52 | W12: 996.08 | X12: 1101.61 | Y12: 1872.89 | Z12: -1150.98 | AA12: 3378.78 | AB12: 1902.04 | AC12: 28869.07 | AD12: 28127.44 | AE12: 18069.59 | AF12: 18716.48 | AG12: 21653.98 | AH12: 21565.7 | AI12: 0.0771 | AJ12: 0.0329 | AK12: 0.1498 | AL12: -0.0416 | AN12: =IF(S12=1,K12,"") | AO12: =IF(S12=1,I12,"") | AP12: =IF(ISNUMBER(J12),J12,"")
A13: IDFC FIRST Bank | B13: IDFCFIRSTB | C13: Private | D13: 71.32 | E13: =T13/U13 -> 860.17 | F13: =D13*E13 -> 61347.324 | G13: =V13+W13 -> 47351.84 | H13: =Z13 -> 1636.36 | I13: =F13/G13 -> 1.2955637 | J13: =IF(H13>0,F13/H13,"n.m.") -> 37.490115 | K13: =H13/((V13+W13+X13+Y13)/2) -> 0.038308863 | L13: =AL13 -> 0.0044 | M13: =(AA13-AB13)/((AC13+AD13)/2) -> 0.05706107 | N13: =AI13 -> 0.0161 | O13: =AJ13 -> 0.0048 | P13: =AK13 -> 0.1373 | Q13: =AE13/AF13-1 -> 0.20281222 | R13: =AG13/AH13-1 -> 0.16824731 | S13: =IF(K13>0.05,1,0) -> 0 | T13: 8601.7 | U13: 10 | V13: 8889.57 | W13: 38462.27 | X13: 7322.11 | Y13: 30755.89 | Z13: 1636.36 | AA13: 40548.82 | AB13: 19333.55 | AC13: 399780.09 | AD13: 343818.65 | AE13: 280390.6 | AF13: 233112.53 | AG13: 294474.55 | AH13: 252065.25 | AI13: 0.0161 | AJ13: 0.0048 | AK13: 0.1373 | AL13: 0.0044 | AN13: =IF(S13=1,K13,"") | AO13: =IF(S13=1,I13,"") | AP13: =IF(ISNUMBER(J13),J13,"") -> 37.490115
A14: Bandhan Bank | B14: BANDHANBNK | C14: Private | D14: 208.3 | E14: =T14/U14 -> 161.097 | F14: =D14*E14 -> 33556.505 | G14: =V14+W14 -> 25574.89 | H14: =Z14 -> 1223.56 | I14: =F14/G14 -> 1.312088 | J14: =IF(H14>0,F14/H14,"n.m.") -> 27.425304 | K14: =H14/((V14+W14+X14+Y14)/2) -> 0.048766937 | L14: =AL14 -> 0.0064 | M14: =(AA14-AB14)/((AC14+AD14)/2) -> 0.053798755 | N14: =AI14 -> 0.0327 | O14: =AJ14 -> 0.0097 | P14: =AK14 -> 0.1804 | Q14: =AE14/AF14-1 -> 0.13725909 | R14: =AG14/AH14-1 -> 0.10007076 | S14: =IF(K14>0.05,1,0) -> 0 | T14: 1610.97 | U14: 10 | V14: 1610.97 | W14: 23963.92 | X14: 1610.97 | Y14: 22994.04 | Z14: 1223.56 | AA14: 21689.11 | AB14: 10859.42 | AC14: 211123.73 | AD14: 191476.29 | AE14: 150103.78 | AF14: 131987.32 | AG14: 166344.45 | AH14: 151212.5 | AI14: 0.0327 | AJ14: 0.0097 | AK14: 0.1804 | AL14: 0.0064 | AN14: =IF(S14=1,K14,"") | AO14: =IF(S14=1,I14,"") | AP14: =IF(ISNUMBER(J14),J14,"") -> 27.425304
A15: RBL Bank | B15: RBLBANK | C15: Private | D15: 345 | E15: =T15/U15 -> 61.811 | F15: =D15*E15 -> 21324.795 | G15: =V15+W15 -> 16604.9 | H15: =Z15 -> 822.44 | I15: =F15/G15 -> 1.2842471 | J15: =IF(H15>0,F15/H15,"n.m.") -> 25.928694 | K15: =H15/((V15+W15+X15+Y15)/2) -> 0.051064691 | L15: =AL15 -> 0.0053 | M15: =(AA15-AB15)/((AC15+AD15)/2) -> 0.038847527 | N15: =AI15 -> 0.0145 | O15: =AJ15 -> 0.0039 | P15: =AK15 -> 0.1277 | Q15: =AE15/AF15-1 -> 0.23336292 | R15: =AG15/AH15-1 -> 0.2530481 | S15: =IF(K15>0.05,1,0) -> 1 | T15: 618.11 | U15: 10 | V15: 618.11 | W15: 15986.79 | X15: 607.88 | Y15: 14998.91 | Z15: 822.44 | AA15: 14335.55 | AB15: 7976.01 | AC15: 180684.81 | AD15: 146725.48 | AE15: 114231.94 | AF15: 92618.27 | AG15: 139017.58 | AH15: 110943.53 | AI15: 0.0145 | AJ15: 0.0039 | AK15: 0.1277 | AL15: 0.0053 | AN15: =IF(S15=1,K15,"") -> 0.051064691 | AO15: =IF(S15=1,I15,"") -> 1.2842471 | AP15: =IF(ISNUMBER(J15),J15,"") -> 25.928694
A16: Federal Bank | B16: FEDERALBNK | C16: Private | D16: 288.95 | E16: =T16/U16 -> 246.43 | F16: =D16*E16 -> 71205.948 | G16: =V16+W16 -> 38705.07 | H16: =Z16 -> 4117.32 | I16: =F16/G16 -> 1.839706 | J16: =IF(H16>0,F16/H16,"n.m.") -> 17.294247 | K16: =H16/((V16+W16+X16+Y16)/2) -> 0.11417069 | L16: =AL16 -> 0.0115 | M16: =(AA16-AB16)/((AC16+AD16)/2) -> 0.028939659 | N16: =AI16 -> 0.0162 | O16: =AJ16 -> 0.002 | P16: =AK16 -> 0.1593 | Q16: =AE16/AF16-1 -> 0.12671792 | R16: =AG16/AH16-1 -> 0.10668849 | S16: =IF(K16>0.05,1,0) -> 1 | T16: 492.86 | U16: 2 | V16: 492.86 | W16: 38212.21 | X16: 491.17 | Y16: 32929.45 | Z16: 4117.32 | AA16: 27695.38 | AB16: 17037.97 | AC16: 387521.49 | AD16: 349004.8 | AE16: 264594.37 | AF16: 234836.39 | AG16: 313909.39 | AH16: 283647.47 | AI16: 0.0162 | AJ16: 0.002 | AK16: 0.1593 | AL16: 0.0115 | AN16: =IF(S16=1,K16,"") -> 0.11417069 | AO16: =IF(S16=1,I16,"") -> 1.839706 | AP16: =IF(ISNUMBER(J16),J16,"") -> 17.294247
A17: City Union Bank | B17: CUB | C17: Private | D17: 255.45 | E17: =T17/U17 -> 74.3 | F17: =D17*E17 -> 18979.935 | G17: =V17+W17 -> 10564.86 | H17: =Z17 -> 1326.23 | I17: =F17/G17 -> 1.7965155 | J17: =IF(H17>0,F17/H17,"n.m.") -> 14.311194 | K17: =H17/((V17+W17+X17+Y17)/2) -> 0.13241458 | L17: =AL17 -> 0.0156 | M17: =(AA17-AB17)/((AC17+AD17)/2) -> 0.032406284 | N17: =AI17 -> 0.0191 | O17: =AJ17 -> 0.0068 | P17: =AK17 -> 0.2082 | Q17: =AE17/AF17-1 -> 0.26485386 | R17: =AG17/AH17-1 -> 0.23269231 | S17: =IF(K17>0.05,1,0) -> 1 | T17: 74.3 | U17: 1 | V17: 74.3 | W17: 10490.56 | X17: 74.1 | Y17: 9392.52 | Z17: 1326.23 | AA17: 6869.76 | AB17: 4039.92 | AC17: 97024.4 | AD17: 77623.21 | AE17: 65875.17 | AF17: 52081.25 | AG17: 78307.95 | AH17: 63525.95 | AI17: 0.0191 | AJ17: 0.0068 | AK17: 0.2082 | AL17: 0.0156 | AN17: =IF(S17=1,K17,"") -> 0.13241458 | AO17: =IF(S17=1,I17,"") -> 1.7965155 | AP17: =IF(ISNUMBER(J17),J17,"") -> 14.311194
A19: Group statistics
A20: SFB median (7 peers) | I20: =MEDIAN(I6:I12) -> 0.85382251 | J20: =MEDIAN(AP6:AP12) -> 15.255475 | K20: =MEDIAN(K6:K12) -> 0.075882369 | L20: =MEDIAN(L6:L12) -> 0.0089 | M20: =MEDIAN(M6:M12) -> 0.060367577 | N20: =MEDIAN(N6:N12) -> 0.026 | O20: =MEDIAN(O6:O12) -> 0.0124 | P20: =MEDIAN(P6:P12) -> 0.1751 | Q20: =MEDIAN(Q6:Q12) -> 0.20901812 | R20: =MEDIAN(R6:R12) -> 0.20366832
A21: Private median (5 peers) | I21: =MEDIAN(I13:I17) -> 1.312088 | J21: =MEDIAN(AP13:AP17) -> 25.928694 | K21: =MEDIAN(K13:K17) -> 0.051064691 | L21: =MEDIAN(L13:L17) -> 0.0064 | M21: =MEDIAN(M13:M17) -> 0.038847527 | N21: =MEDIAN(N13:N17) -> 0.0162 | O21: =MEDIAN(O13:O17) -> 0.0048 | P21: =MEDIAN(P13:P17) -> 0.1593 | Q21: =MEDIAN(Q13:Q17) -> 0.20281222 | R21: =MEDIAN(R13:R17) -> 0.16824731
A22: All-peer median (12) | I22: =MEDIAN(I6:I17) -> 1.2899054 | J22: =MEDIAN(AP6:AP17) -> 16.636544 | K22: =MEDIAN(K6:K17) -> 0.06347353 | L22: =MEDIAN(L6:L17) -> 0.00765 | M22: =MEDIAN(M6:M17) -> 0.055429913 | N22: =MEDIAN(N6:N17) -> 0.025 | O22: =MEDIAN(O6:O17) -> 0.0082 | P22: =MEDIAN(P6:P17) -> 0.17095 | Q22: =MEDIAN(Q6:Q17) -> 0.20591517 | R22: =MEDIAN(R6:R17) -> 0.18595782
A23: P/E medians ignore loss-makers (n.m.).
A25: P/B vs ROE cross-section (profitable peers with ROE > 5%)
A26: Peer rows used (1 = include) | C26: =SUM(S6:S17) -> 7
A27: Slope (P/B per 1.00 of ROE) | C27: =SLOPE(AO6:AO17,AN6:AN17) -> 9.0504888
A28: Intercept | C28: =INTERCEPT(AO6:AO17,AN6:AN17) -> 0.48197687
A29: R-squared | C29: =RSQ(AO6:AO17,AN6:AN17) -> 0.3681024
A30: Peer-implied P/B at AU FY26 ROE | C30: =C28+C27*K5 -> 1.7692538
A31: AU actual P/B | C31: =I5 -> 3.6889916
A32: Caution: small sample, single year, ROE depressed by one-offs for several peers; regression is descriptive only.

Sheet Beta
A1: Beta: AUBANK vs NIFTY 50, weekly closes 31-May-2024 to 29-May-2026 [S15][S16]
A3: Week end | B3: AUBANK close | C3: NIFTY 50 | D3: AU log ret | E3: NIFTY log ret | F3: Result
A4: 2024-05-31 | B4: 653.1 | C4: 22530.7 | F4: =SLOPE(D5:D108,E5:E108) -> 1.0232624
A5: 2024-06-07 | B5: 669 | C5: 23290.15 | D5: =LN(B5/B4) -> 0.024053803 | E5: =LN(C5/C4) -> 0.033151701 | F5: =CORREL(D5:D108,E5:E108) -> 0.45613513
A6: 2024-06-14 | B6: 661.25 | C6: 23465.6 | D6: =LN(B6/B5) -> -0.011652077 | E6: =LN(C6/C5) -> 0.0075049945 | F6: =0.67*F4+0.33 -> 1.0155858
A7: 2024-06-21 | B7: 667.6 | C7: 23501.1 | D7: =LN(B7/B6) -> 0.0095572086 | E7: =LN(C7/C6) -> 0.0015117096 | F7: F4 = raw OLS beta (used); F5 = correlation; F6 = Blume-adjusted (reference). Week-end = last trading day of each week.
A8: 2024-06-28 | B8: 672.05 | C8: 24010.6 | D8: =LN(B8/B7) -> 0.0066435507 | E8: =LN(C8/C7) -> 0.021448171
A9: 2024-07-05 | B9: 672.6 | C9: 24323.85 | D9: =LN(B9/B8) -> 0.00081805679 | E9: =LN(C9/C8) -> 0.012961951
A10: 2024-07-12 | B10: 643.8 | C10: 24502.15 | D10: =LN(B10/B9) -> -0.04376268 | E10: =LN(C10/C9) -> 0.0073035183
A11: 2024-07-19 | B11: 633.65 | C11: 24530.9 | D11: =LN(B11/B10) -> -0.015891367 | E11: =LN(C11/C10) -> 0.0011726786
A12: 2024-07-26 | B12: 650.4 | C12: 24834.85 | D12: =LN(B12/B11) -> 0.026090807 | E12: =LN(C12/C11) -> 0.012314361
A13: 2024-08-02 | B13: 637.6 | C13: 24717.7 | D13: =LN(B13/B12) -> -0.019876431 | E13: =LN(C13/C12) -> -0.0047283225
A14: 2024-08-09 | B14: 625.95 | C14: 24367.5 | D14: =LN(B14/B13) -> -0.018440632 | E14: =LN(C14/C13) -> -0.014269309
A15: 2024-08-16 | B15: 613.2 | C15: 24541.15 | D15: =LN(B15/B14) -> -0.020579349 | E15: =LN(C15/C14) -> 0.0071010232
A16: 2024-08-23 | B16: 625.8 | C16: 24823.15 | D16: =LN(B16/B15) -> 0.020339684 | E16: =LN(C16/C15) -> 0.011425385
A17: 2024-08-30 | B17: 688.7 | C17: 25235.9 | D17: =LN(B17/B16) -> 0.095774931 | E17: =LN(C17/C16) -> 0.016490898
A18: 2024-09-06 | B18: 703 | C18: 24852.15 | D18: =LN(B18/B17) -> 0.020551129 | E18: =LN(C18/C17) -> -0.015323316
A19: 2024-09-13 | B19: 722.9 | C19: 25356.5 | D19: =LN(B19/B18) -> 0.027914008 | E19: =LN(C19/C18) -> 0.02009084
... A108: 2026-05-29 | B108: 984.7 | C108: 23547.75 | D108: =LN(B108/B107) -> 0.0069296109 | E108: =LN(C108/C107) -> -0.0072587882

Sheet Checks
A1: Model Integrity Checks
A2: Overall Status | B2: =IF(COUNTIF(C4:C23,"FAIL")=0,"ALL CHECKS PASS","CHECK FAILURES: "&COUNTIF(C4:C23,"FAIL")) -> ALL CHECKS PASS
A4: Hist: interest earned sub-items sum to reported (all years, abs diff Rs cr) | B4: =SUMPRODUCT(ABS(Hist!C10:H10-Hist!C25:H25)) -> 0 | C4: =IF(B4<=0.01,"PASS","FAIL") -> PASS
A5: Hist: PBT rebuilt from components equals reported PBT | B5: =SUMPRODUCT(ABS(Hist!C21:H21-Hist!C26:H26)) -> 3.8653525e-12 | C5: =IF(B5<=0.01,"PASS","FAIL") -> PASS
A6: Hist: PAT rebuilt equals reported PAT | B6: =SUMPRODUCT(ABS(Hist!C23:H23-Hist!C24:H24)) -> 0.0001 | C6: =IF(B6<=0.01,"PASS","FAIL") -> PASS
A7: Hist: total assets = total liabilities & equity (sum of abs diffs) | B7: =SUMPRODUCT(ABS(Hist!C35:H35-Hist!C43:H43)) -> 1.4551915e-11 | C7: =IF(B7<=0.01,"PASS","FAIL") -> PASS
A8: Hist: total liabilities & equity equals reported total | B8: =SUMPRODUCT(ABS(Hist!C43:H43-Hist!C44:H44)) -> 1.4551915e-11 | C8: =IF(B8<=0.01,"PASS","FAIL") -> PASS
A9: Hist: CRAR from Pillar 3 capital/RWA equals reported CRAR (max abs diff, FY22-26) | B9: =MAX(ABS(Hist!D58-Hist!D60),ABS(Hist!E58-Hist!E60),ABS(Hist!F58-Hist!F60),ABS(Hist!G58-Hist!G60),ABS(Hist!H58-Hist!H60)) -> 3.7571466e-05 | C9: =IF(B9<=0.01,"PASS","FAIL") -> PASS
A10: Model: FY26A segment GLP sums to reported GLP 140,327 | B10: =ABS(Model!E18-140327) -> 0 | C10: =IF(B10<=0.01,"PASS","FAIL") -> PASS
A11: Model: FY26A PAT equals Hist PAT | B11: =ABS(Model!E70-Hist!H23) -> 0 | C11: =IF(B11<=0.01,"PASS","FAIL") -> PASS
A12: Model: balance sheet balances every year (sum of abs diffs) | B12: =SUMPRODUCT(ABS(Model!C44:J44)) -> 0 | C12: =IF(B12<=0.01,"PASS","FAIL") -> PASS
A13: Model: equity roll-forward closing = capital + reserves (forecast) | B13: =SUMPRODUCT(ABS(Model!F80:J80-Model!F81:J81-Model!F82:J82)) -> 0 | C13: =IF(B13<=0.01,"PASS","FAIL") -> PASS
A14: Model: retained-earnings movement = PAT - dividends paid (forecast) | B14: =SUMPRODUCT(ABS((Model!F82:J82-Model!E82:I82)-(Model!F77:J77+Model!F78:J78-(Model!F81:J81-Model!E81:I81))-(Model!F70:J70-Model!F76:J76))) -> 5.9117156e-12 | C14: =IF(B14<=0.01,"PASS","FAIL") -> PASS
A15: Model: share count roll-forward (closing = opening + ESOP + new issue) | B15: =SUMPRODUCT(ABS(Model!F83:J83-Model!E83:I83-Inputs!C159:G159-Inputs!C164:G164/(Inputs!C169:G169*Model!E84:I84))) -> 2.8310687e-14 | C15: =IF(B15<=0.01,"PASS","FAIL") -> PASS
A16: Model: capital ratio consistency - CET1 <= CRAR and Tier 2 <= Tier 1 every year | B16: =SUMPRODUCT((Model!C99:J99>Model!C100:J100)+(Model!C93:J93>Model!C92:J92)) -> 0 | C16: =IF(B16<=0.01,"PASS","FAIL") -> PASS
A17: Model: CRAR >= regulatory minimum every forecast year (count of breaches) | B17: =SUMPRODUCT(--(Model!F104:J104<0)) -> 0 | C17: =IF(B17<=0.01,"PASS","FAIL") -> PASS
A18: Model: CET1 >= internal floor every forecast year (count of breaches) | B18: =SUMPRODUCT(--(Model!F105:J105<0)) -> 0 | C18: =IF(B18<=0.01,"PASS","FAIL") -> PASS
A19: Model: cash & bank >= minimum liquidity every forecast year (count of breaches) | B19: =SUMPRODUCT(--(Model!F47:J47<Inputs!C36)) -> 0 | C19: =IF(B19<=0.01,"PASS","FAIL") -> PASS
A20: Model: CD ratio <= funding cap every forecast year (count of breaches) | B20: =SUMPRODUCT(--(Model!F26:J26>Inputs!C37)) -> 0 | C20: =IF(B20<=0.01,"PASS","FAIL") -> PASS
A21: Valuation: CoE > terminal growth | B21: =IF(Valuation!B5>Valuation!B6,0,1) -> 0 | C21: =IF(B21<=0.01,"PASS","FAIL") -> PASS
A22: Valuation: implied fade payout between 0% and 100% | B22: =SUMPRODUCT((Valuation!H25:Q25<0)+(Valuation!H25:Q25>1)) -> 0 | C22: =IF(B22<=0.01,"PASS","FAIL") -> PASS
A23: Sensitivity grid reproduces value/share | B23: =IFERROR(ABS(INDEX(Valuation!C72:I72,MATCH(Valuation!B7,Valuation!C67:I67,0))-Valuation!B36),0) -> 0 | C23: =IF(B23<=0.01,"PASS","FAIL") -> PASS

Sheet DataDict
A1: Data Dictionary and Definitions
A3: Metric | B3: Model definition (used consistently for history, forecast and peers where stated)
A4: Gross loan portfolio (GLP) | B4: Company-reported gross advances including off-book (securitised/IBPC) and before provisions; segment split per loan-mix slide
A5: Net advances | B5: Balance-sheet advances (net of provisions)
A6: Yield on advances | B6: Interest/discount on advances / simple average of opening and closing net advances
A7: Cost of funds (CoF) | B7: Interest expended / simple average of (deposits + borrowings)
A8: NIM | B8: NII / simple average interest-earning assets (net advances + investments + cash & bank balances)
A9: Other income ratio | B9: Other income / average non-cash assets (net adv + investments + fixed + other assets)
A10: Opex ratio | B10: Operating expenses / average non-cash assets; also shown / avg total assets (company style)
A11: Cost-to-income | B11: Operating expenses / (NII + other income)
A12: Credit cost | B12: Provisions & contingencies (ex tax) / average GLP
A13: GNPA / NNPA ratio | B13: As reported: gross NPA / gross advances; net NPA / net advances
A14: Specific PCR | B14: 1 - NNPA / GNPA (excludes technical write-offs)
... A25: Peer NII / assets | B25: (Interest earned - interest expended) / avg total assets

Sheet Sources
A1: Source log (primary sources only; all published on or before the 29-May-2026 cut-off)
A3: ID | B3: Document | C3: Period | D3: Published | E3: Page / table / tag | F3: URL | G3: Units | H3: Used for
A4: S1 | B4: AU SFB - Audited financial results Q4 & FY26 (Reg 33), standalone | C4: FY26, FY25 | D4: 27-Apr-2026 | E4: Statement of results; Statement of assets & liabilities; notes (dividend, ESOP allotment, CFO, fund-raise enabling) | F4: https://www.au.bank.in/pdfs/quaterly-reports/year-25/financial-result/Q4FY26-Result.pdf | G4: INR lakh | H4: Hist FY25-FY26 P&L/BS, EPS, NPA, CRAR
A5: S2 | B5: NSE Integrated Filing - Financials XBRL, AU SFB, standalone, FY26 audited | C5: FY26 | D5: 27-Apr-2026 | E5: XBRL tags (InterestEarned, ..., CET1Ratio, Deposits, Advances) | F5: https://nsearchives.nseindia.com/corporate/xbrl/INTEGRATED_FILING_BANKING_1659849_27042026112414_WEB.xml | G5: INR (rupees) | H5: Hist FY26 verification; Peers AU row
A6: S3 | B6: AU SFB - Audited financial results Q4 & FY24 (standalone) | C6: FY24, FY23 | D6: 24-Apr-2024 | E6: Statement of results; assets & liabilities; notes (Fincare scheme, exceptional item) | F6: https://www.au.bank.in/pdfs/quaterly-reports/year-23/financial-result/Q4FY24-Financial-Result.pdf | G6: INR lakh | H6: Hist FY23-FY24
A7: S4 | B7: AU SFB - Audited financial results Q4 & FY22 (standalone) | C7: FY22, FY21 (regrouped) | D7: 26-Apr-2022 | E7: Statement of results; assets & liabilities; notes (dividend, 1:1 bonus) | F7: https://www.au.bank.in/pdfs/quaterly-reports/year-21/financial-result/Q4FY22-Financial-Results.pdf | G7: INR lakh | H7: Hist FY21-FY22
A8: S5 | B8: NSE legacy results XBRL, AU SFB, Q4 filings FY21-FY24 (annual context) | C8: FY21-FY24 | D8: 30-Apr-2021; 27-Apr-2022; 26-Apr-2023; 25-Apr-2024 | E8: Context FourD | F8: https://nsearchives.nseindia.com/corporate/xbrl/BANKING_69558_445061_30042021021223_WEB.xml ; ..._83651_648527_27042022042456_WEB.xml ; ..._90859_833207_26042023041609.xml ; ..._104695_1107810_25042024013649.xml | G8: INR (rupees) | H8: Verification of FY21-FY24 P&L
A9: S6 | B9: AU SFB - Basel II Pillar 3 disclosures at 31-Mar-2026 | C9: Mar-26 | D9: not stated on document (year-end disclosure) | E9: Capital funds, RWA, DF-2 ratios; regulatory minima (CET1 6%, Tier-1 7.5%, CRAR 15%) | F9: https://www.au.bank.in/pdfs/regulatory-disclosures/2025-2026/PILLAR-3-Disclosures-at_March-31-2026.pdf | G9: INR crore | H9: Tier 1, Tier 2, RWA FY26; SFB minima
A10: S7 | B10: AU SFB - Basel II Pillar 3 disclosures at 31-Mar-2025 / 2024 / 2023 / 2022 | C10: Mar-22 to Mar-25 | D10: year-end disclosures | E10: Capital funds position; capital requirement table | F10: https://www.au.bank.in/pdfs/regulatory-disclosures/2024-2025/basel-ll-pillar-lll-disclosures-basel-ii-pillar-3-disclosuresat-march-31-2025.pdf (and 2023-24, 2022-23, 2021-22 equivalents on the Regulatory Disclosures page) | G10: INR lakh | H10: Tier 1, Tier 2, RWA FY22-FY25
A11: S8 | B11: AU SFB - Q4FY26 earnings presentation | C11: Q4FY26 / FY26 | D11: 27-Apr-2026 | E11: Loan-mix slide (GLP by segment Mar-26/Dec-25/Mar-25); deposits; NIM/CoF; asset quality | F11: https://www.au.bank.in/pdfs/quaterly-reports/year-25/investors-presentation/Q4FY26-PPT.pdf | G11: INR crore | H11: Segment GLP, company-reported NIM, CoF, CASA
A12: S9 | B12: AU SFB - Q4FY26 results press release | C12: Q4FY26 / FY26 | D12: 27-Apr-2026 | E12: Headline metrics | F12: https://www.au.bank.in/pdfs/press-release/2026/PR-final-27th-Apr.pdf | G12: INR crore | H12: CASA 43,357 cr (28%), GLP 140,327, BVPS 267, ROE 14.2%, credit cost 0.96% of avg assets, LCR 119%, touchpoints 2,790
A13: S10 | B13: AU SFB - Q4FY26 earnings call transcript | C13: Q4FY26 | D13: Call Date 27-Apr-2026 | E13: Management commentary | F13: https://www.au.bank.in/pdfs/quaterly-reports/year-25/call-transcript/AUSFB-Q4FY26-Transcript.pdf | G13: n/a | H13: Guidance: growth 2-2.5x nominal GDP; ROA ~1.8% aspiration FY27; credit cost ~90bp (of assets); opex/assets <4% FY27
A14: S11 | B14: AU SFB - Q4FY24 investor presentation | C14: Q4FY24 / FY24 | D14: 24-Apr-2024 | E14: CASA, NIM, CoF, loan mix Mar-24 | F14: https://www.au.bank.in/pdfs/quaterly-reports/year-23/investors-presentation/Q4FY24-investor-ppt-vf.pdf | G14: INR crore | H14: CASA FY23-FY24, company NIM/CoF FY23-FY24, GLP Mar-24
... A23: S20 | B23: RBI Weekly Statistical Supplement extract (press release, 29-May-2026), Table 4: Scheduled Commercial Banks - Business in India | C23: as on 15-May-2026 | D23: 29-May-2026 | E23: Aggregate deposits YoY +12.2%; bank credit YoY +16.2% | F23: https://www.rbi.org.in/Scripts/BS_PressReleaseDisplay.aspx?prid=62826 | G23: INR crore / % | H23: System growth context for funding-supportability test
